Workbook

Sheet Dashboard
A1: India Startup Funding Tracker
A2: Rounds announced 02 Jan 2025 to 10 Oct 2026, cross-checked across Entrackr, Inc42, The Economic Times, VCCircle. Built 11 Oct 2026.
A4: Rounds tracked | D4: Disclosed funding, USD bn | G4: Median round, USD mn | J4: Source reports matched | M4: Duplicate reports merged | P4: Amount disagreements over 10%
A5: =COUNTA(Rounds!$A$2:$A$2179) -> 2178 | D5: =SUM(Rounds!$E$2:$E$2179)/1000 -> 28.468859 | G5: =MEDIAN(Rounds!$E$2:$E$2179) -> 3.5 | J5: =COUNTA(Reports!$A$5:$A$4463) -> 4459 | M5: =J5-A5 -> 2281 | P5: =COUNTIF(Rounds!$P$2:$P$2179,">10") -> 68
A6: 70% confirmed by 2+ sources | D6: 2,013 rounds disclosed an amount | G6: half of disclosed rounds are smaller | J6: articles, table rows and headlines | M6: 228 needed name matching | P6: rounds where sources differ
A23: The last month shown is partial: data runs to 10 Oct 2026.
A46: Look up a round
A47: Round ID | C47: R261010-nathabit | F47: pick an ID from the list, or paste one from the Rounds sheet
A48: Company | C48: =IFERROR(IF(INDEX(Rounds!$B$2:$B$2179,MATCH($C$47,Rounds!$A$2:$A$2179,0))="","",INDEX(Rounds!$B$2:$B$2179,MATCH($C$47,Rounds!$A$2:$A$2179,0))),"not found") -> Nat Habit
A49: Announced | C49: =IFERROR(IF(INDEX(Rounds!$C$2:$C$2179,MATCH($C$47,Rounds!$A$2:$A$2179,0))="","",INDEX(Rounds!$C$2:$C$2179,MATCH($C$47,Rounds!$A$2:$A$2179,0))),"not found") -> 46305
A50: Amount (USD mn) | C50: =IFERROR(IF(INDEX(Rounds!$E$2:$E$2179,MATCH($C$47,Rounds!$A$2:$A$2179,0))="","",INDEX(Rounds!$E$2:$E$2179,MATCH($C$47,Rounds!$A$2:$A$2179,0))),"not found") -> 14.68
A51: As reported | C51: =IFERROR(IF(INDEX(Rounds!$G$2:$G$2179,MATCH($C$47,Rounds!$A$2:$A$2179,0))="","",INDEX(Rounds!$G$2:$G$2179,MATCH($C$47,Rounds!$A$2:$A$2179,0))),"not found") -> Rs 142 crore
A52: Stage | C52: =IFERROR(IF(INDEX(Rounds!$H$2:$H$2179,MATCH($C$47,Rounds!$A$2:$A$2179,0))="","",INDEX(Rounds!$H$2:$H$2179,MATCH($C$47,Rounds!$A$2:$A$2179,0))),"not found") -> Undisclosed
A53: Sector | C53: =IFERROR(IF(INDEX(Rounds!$J$2:$J$2179,MATCH($C$47,Rounds!$A$2:$A$2179,0))="","",INDEX(Rounds!$J$2:$J$2179,MATCH($C$47,Rounds!$A$2:$A$2179,0))),"not found") -> Ecommerce
A54: City | C54: =IFERROR(IF(INDEX(Rounds!$K$2:$K$2179,MATCH($C$47,Rounds!$A$2:$A$2179,0))="","",INDEX(Rounds!$K$2:$K$2179,MATCH($C$47,Rounds!$A$2:$A$2179,0))),"not found") -> Unknown
A55: Lead investors | C55: =IFERROR(IF(INDEX(Rounds!$L$2:$L$2179,MATCH($C$47,Rounds!$A$2:$A$2179,0))="","",INDEX(Rounds!$L$2:$L$2179,MATCH($C$47,Rounds!$A$2:$A$2179,0))),"not found") -> Trident Growth Partners
A56: Sources | C56: =IFERROR(IF(INDEX(Rounds!$N$2:$N$2179,MATCH($C$47,Rounds!$A$2:$A$2179,0))="","",INDEX(Rounds!$N$2:$N$2179,MATCH($C$47,Rounds!$A$2:$A$2179,0))),"not found") -> et
A57: Flags | C57: =IFERROR(IF(INDEX(Rounds!$Q$2:$Q$2179,MATCH($C$47,Rounds!$A$2:$A$2179,0))="","",INDEX(Rounds!$Q$2:$Q$2179,MATCH($C$47,Rounds!$A$2:$A$2179,0))),"not found") -> C04 C07
A59: Flags are check IDs from the Checks sheet. PivotTables are on the By Sector, By Stage and By City sheets and refresh when the file opens.

Sheet Rounds
A1: Round ID | B1: Company | C1: Announced | D1: Month | E1: Amount (USD mn) | F1: Amount (INR cr) | G1: As reported | H1: Stage | I1: Stage group | J1: Sector | K1: City | L1: Lead investors | M1: Investors | N1: Sources | O1: Source count | P1: Amount spread % | Q1: Flags | R1: First source link
A2: R250102-ayefinance | B2: Aye Finance | C2: 45659 | D2: 45658 | E2: 12.8 | F2: 109.77 | G2: $12.8 Mn | H2: Debt | I2: Debt | J2: Fintech | K2: Unknown | M2: Northern Arc; ASK Financial Holdings; MAS Financial Services; CredAvenue | N2: inc42 | O2: 1 | P2: 0 | Q2: C07 | R2: https://inc42.com/buzz/from-aye-finance-to-klassroom-indian-startups-raised-14-mn-this-week/
A3: R250102-cargofl | B3: CargoFL | C3: 45659 | D3: 45658 | E3: 0.787 | F3: 6.75 | G3: Rs 6.75 crore | H3: Seed | I3: Early | J3: Logistics | K3: Pune | L3: YourNest Venture Capital | M3: YourNest Venture Capital; Real Time Angel Fund; Peaceful Progress Angel Fund; Sanchi Connect Accelerator; Dinesh Chandra Agarwal; Dinesh Gulati; Murugavel Janakiraman; Rajesh Sawhney | N3: entrackr | inc42 | O3: 2 | P3: 0 | R3: https://entrackr.com/snippets/cargofl-raises-seed-funding-round-8584928
A4: R250102-klassroom | B4: Klassroom | C4: 45659 | D4: 45658 | H4: Pre-Series A | I4: Early | J4: Edtech | K4: Unknown | M4: LetsVenture; Hem Securities; Meteor Ventures; Growth Sense Fund | N4: inc42 | O4: 1 | Q4: C03 C07 | R4: https://inc42.com/buzz/from-aye-finance-to-klassroom-indian-startups-raised-14-mn-this-week/
A5: R250104-oyo | B5: OYO | C5: 45661 | D5: 45658 | E5: 64.125 | F5: 550 | G5: Rs 550 crore | H5: Undisclosed | I5: Undisclosed | J5: Travel Tech | K5: Delhi NCR | L5: Redsprig Innovation Partners | M5: Redsprig Innovation Partners; Ritesh Agarwal | N5: entrackr | inc42 | O5: 2 | P5: 1.4 | Q5: C04 | R5: https://entrackr.com/news/oyo-raises-65-mn-from-ritesh-agarwals-redsprig-innovation-8591029
A6: R250106-blackcarrot | B6: BlackCarrot | C6: 45663 | D6: 45658 | H6: Seed | I6: Early | J6: Ecommerce | K6: Unknown | L6: Circle | M6: Circle; EvolveX accelerator; Suraj Nalin | N6: inc42 | O6: 1 | Q6: C03 C07 | R6: https://inc42.com/buzz/from-innovaccer-to-beyond-snack-indian-startups-raised-432-mn-this-week/
A7: R250106-consintai | B7: Consint.AI | C7: 45663 | D7: 45658 | E7: 0.584 | F7: 5 | G7: Rs 5 crore | H7: Seed | I7: Early | J7: Artificial Intelligence | K7: Delhi NCR | L7: Equanimity Ventures; Seafund | M7: Equanimity Ventures; Seafund | N7: entrackr | et | O7: 2 | P7: 0 | R7: https://entrackr.com/snippets/genai-startup-consintai-raises-rs-5-cr-in-seed-round-8594981
A8: R250106-spintly | B8: Spintly | C8: 45663 | D8: 45658 | E8: 0.409 | F8: 3.5 | G8: Rs 3.5 crore | H8: Seed | I8: Early | J8: Deeptech | K8: Goa | L8: Spyre VC; Chakra Growth Fund; Alumni Ventures; Doctor Technology | M8: Spyre VC; Chakra Growth Fund; Alumni Ventures; Doctor Technology; Accel India | N8: entrackr | inc42 | O8: 2 | P8: 0.4 | R8: https://entrackr.com/snippets/proptech-startup-spintly-raises-rs-35-cr-in-extended-seed-round-8594970
A9: R250107-bodmastechnolo | B9: Bodmas Technologies | C9: 45664 | D9: 45658 | H9: Undisclosed | I9: Undisclosed | J9: Enterprise Tech | K9: Unknown | M9: Auxano Capital | N9: inc42 | O9: 1 | Q9: C03 C04 C07 | R9: https://inc42.com/buzz/from-innovaccer-to-beyond-snack-indian-startups-raised-432-mn-this-week/
A10: R250107-emoenergy | B10: EMO Energy | C10: 45664 | D10: 45658 | E10: 6.2 | F10: 53.16 | G10: $6.2 million | H10: Series A | I10: Early | J10: Cleantech | K10: Bengaluru | L10: Subhkam Ventures; Transition VC | M10: Subhkam Ventures; Transition VC; Microtek Group; SRK Family Office | N10: entrackr | inc42 | et | O10: 3 | P10: 0 | R10: https://entrackr.com/snippets/emo-energy-raises-62-mn-in-series-a-round-8598190
A11: R250107-kibisports | B11: KIBI Sports | C11: 45664 | D11: 45658 | E11: 0.1 | F11: 0.86 | G11: $100,000 | H11: Pre-Seed | I11: Early | J11: Media & Entertainment | K11: Bengaluru | M11: Saurabh Aggarwal; Arpit Bhardwaj; Vartika Joshi; Suryansh Jain; Pranjal Bansal; Amit Kumar Sahu; Pratibha Rani; Sushila | N11: entrackr | O11: 1 | P11: 0 | R11: https://entrackr.com/snippets/kibi-sports-raises-100k-in-pre-seed-funding-8598246
A12: R250107-moonrider | B12: Moonrider | C12: 45664 | D12: 45658 | E12: 2.2 | F12: 18.86 | G12: $2.2 million | H12: Seed | I12: Early | J12: Cleantech | K12: Bengaluru | L12: Micelio Fund | M12: Micelio Fund | N12: entrackr | inc42 | et | O12: 3 | P12: 0 | R12: https://entrackr.com/snippets/electric-tractor-startup-moonrider-raises-22-mn-in-seed-round-8597800
A13: R250107-obenelectric | B13: Oben Electric | C13: 45664 | D13: 45658 | E13: 5.832 | F13: 50 | G13: Rs 50 crore | H13: Series A | I13: Early | J13: Cleantech | K13: Bengaluru | M13: Ambis Holding US; Kuberans Ventures; Karimjee Group; Mission Vertical Capital; Sanjeev Saraf | N13: entrackr | inc42 | O13: 2 | P13: 0.5 | R13: https://entrackr.com/snippets/oben-electric-raises-6-mn-in-series-a-8598547
A14: R250107-pratilipi | B14: Pratilipi | C14: 45664 | D14: 45658 | E14: 1.2 | F14: 10.29 | G14: $1.2 Mn | H14: Undisclosed | I14: Undisclosed | J14: Media & Entertainment | K14: Delhi NCR | L14: Alteria Capital | M14: Alteria Capital | N14: inc42 | O14: 1 | P14: 0 | Q14: C04 | R14: https://inc42.com/buzz/from-innovaccer-to-beyond-snack-indian-startups-raised-432-mn-this-week/
A15: R250107-vehanttechnolo | B15: Vehant Technologies | C15: 45664 | D15: 45658 | E15: 9 | F15: 77.17 | G15: $9 million | H15: Debt | I15: Debt | J15: Unclassified | K15: Delhi NCR | M15: True North | N15: entrackr | et | O15: 2 | P15: 0 | Q15: C06 | R15: https://economictimes.indiatimes.com/tech/funding/vehant-technologies-raises-9-million-from-true-north-through-ncds-plans-ipo-by-2026/articleshow/117013023.cms
A16: R250107-zoplar | B16: Zoplar | C16: 45664 | D16: 45658 | E16: 3.4 | F16: 29.15 | G16: $3.4 million | H16: Series A | I16: Early | J16: Healthtech | K16: Delhi NCR | L16: Blume Ventures | M16: Blume Ventures; BEENEXT; Saison Capital; Finfirst; LogX Ventures | N16: entrackr | inc42 | O16: 2 | P16: 0 | R16: https://entrackr.com/snippets/blume-ventures-leads-34-mn-round-in-zoplar-8598758
A17: R250108-brainsightai | B17: BrainSinghtAI | C17: 45665 | D17: 45658 | E17: 5 | F17: 42.94 | G17: $5 million | H17: Pre-Series A | I17: Early | J17: Healthtech | K17: Bengaluru | L17: IAN Alpha Fund; Silver Needle | M17: IAN Alpha Fund; IvyCap Ventures; Silver Needle | N17: entrackr | inc42 | et | O17: 3 | P17: 0 | R17: https://entrackr.com/snippets/neuroscience-startup-brainsight-ai-raises-5-mn-8602138
A18: R250108-hbits | B18: hBits | C18: 45665 | D18: 45658 | E18: 4.657 | F18: 40 | G18: Rs 40 crore | H18: Series A | I18: Early | J18: Fintech | K18: Mumbai | L18: Capricon Realty | M18: Capricon Realty | N18: entrackr | inc42 | O18: 2 | P18: 1.2 | R18: https://entrackr.com/snippets/proptech-startup-hbits-raises-rs-40-cr-in-series-a-8601862
A19: R250108-rasluxuryskinc | B19: RAS Luxury Skincare | C19: 45665 | D19: 45658 | E19: 5 | F19: 42.94 | G19: $5 million | H19: Series A | I19: Early | J19: Ecommerce | K19: Raipur | L19: Unilever Ventures | M19: Unilever Ventures; Amazon Smbhav Venture Fund; Sixth Sense Ventures | N19: entrackr | inc42 | et | O19: 3 | P19: 0 | R19: https://entrackr.com/snippets/ras-luxury-skincare-raises-5-mn-led-by-unilever-ventures-8600516
A20: R250109-beyondsnack | B20: Beyond Snack | C20: 45666 | D20: 45658 | E20: 8.3 | F20: 71.26 | G20: $8.3 million | H20: Series A | I20: Early | J20: Ecommerce | K20: Unknown | L20: 12 Flags Group | M20: 12 Flags Group; NAB Ventures; Enrission India Capital; FAAD Network | N20: entrackr | inc42 | et | vccircle | O20: 4 | P20: 0 | Q20: C07 | R20: https://entrackr.com/snippets/beyond-snack-raises-83-mn-in-series-a-round-8604226
A21: R250109-grayquest | B21: GrayQuest | C21: 45666 | D21: 45658 | E21: 9.319 | F21: 80 | G21: Rs 80 crore | H21: Series B | I21: Growth | J21: Fintech | K21: Mumbai | L21: IIFL Fintech Fund; Claypond Capital | M21: IIFL Fintech Fund; Claypond Capital; Pravega Ventures; Weizmann Group; Telama Family Office; Apurva Parekh from the Pidilite Family Office | N21: entrackr | inc42 | et | vccircle | O21: 4 | P21: 0.2 | R21: https://entrackr.com/news/grayquest-raises-93-mn-from-iifl-fintech-fund-claypond-and-pravega-8605812
A22: R250109-infinityfincor | B22: Infinity Fincorp | C22: 45666 | D22: 45658 | E22: 35 | F22: 300.48 | G22: $35 million | H22: Undisclosed | I22: Undisclosed | J22: Fintech | K22: Mumbai | L22: Jungle Ventures | M22: Jungle Ventures; Archerman Capital; Magnifico | N22: entrackr | inc42 | et | O22: 3 | P22: 133.3 | Q22: C04 C15 | R22: https://entrackr.com/snippets/infinity-fincorp-solutions-closes-35-mn-round-8603735
A23: R250109-innovaccer | B23: Innovaccer | C23: 45666 | D23: 45658 | E23: 275 | F23: 2360.88 | G23: $275 million | H23: Series F | I23: Late | J23: Healthtech | K23: Unknown | M23: B Capital Group; Banner Health; Danaher Ventures LLC; Generation Investment Management; Kaiser Permanente; M12 | N23: entrackr | inc42 | et | vccircle | O23: 4 | P23: 0 | Q23: C07 | R23: https://economictimes.indiatimes.com/tech/funding/saas-firm-innovaccer-closes-275-million-funding-to-build-more-on-ai-cloud/articleshow/117092526.cms
A24: R250109-integrishealth | B24: Integris Health | C24: 45666 | D24: 45658 | H24: Undisclosed | I24: Undisclosed | J24: Healthtech | K24: Unknown | M24: Mukul Agarwal; India SME Fund; Everstone Capital | N24: entrackr | O24: 1 | Q24: C03 C04 C07 | R24: https://entrackr.com/snippets/integris-health-raises-primary-capital-ahead-of-planned-ipo-8604374
A25: R250109-revivo | B25: Revivo | C25: 45666 | D25: 45658 | H25: Pre-Series A | I25: Early | J25: Consumer Services | K25: Unknown | L25: Inflection Point Ventures | M25: Inflection Point Ventures | N25: inc42 | O25: 1 | Q25: C03 C07 | R25: https://inc42.com/buzz/from-innovaccer-to-beyond-snack-indian-startups-raised-432-mn-this-week/
A26: R250109-waycool | B26: WayCool | C26: 45666 | D26: 45658 | E26: 4.4 | F26: 37.77 | G26: $4.4 Mn | H26: Undisclosed | I26: Undisclosed | J26: Agritech | K26: Chennai | L26: Trifecta Capital | M26: Trifecta Capital; Alteria Capital; Stride Ventures | N26: inc42 | O26: 1 | P26: 0 | Q26: C04 | R26: https://inc42.com/buzz/from-innovaccer-to-beyond-snack-indian-startups-raised-432-mn-this-week/
A27: R250110-quash | B27: Quash | C27: 45667 | D27: 45658 | E27: 0.635 | F27: 5.46 | G27: $635,000 | H27: Pre-Seed | I27: Early | J27: Enterprise Tech | K27: Bengaluru | L27: Arali Ventures | M27: Arali Ventures; Java Capital; PeerCheque; DeVC; Abhishek Goyal | N27: entrackr | inc42 | O27: 2 | P27: 0 | R27: https://entrackr.com/snippets/agentic-ai-startup-quash-raises-pre-seed-round-led-by-arali-ventures-8608038
A28: R250110-reputai | B28: RePut.ai | C28: 45667 | D28: 45658 | E28: 1 | F28: 8.6 | G28: $1 million | H28: Pre-Seed | I28: Early | J28: Enterprise Tech | K28: Bengaluru | L28: GrowthCap Venture | M28: GrowthCap Ventures; Vipul Parekh; Abhijeet Kumar; Vishal Jain; Anshul Sharan | N28: entrackr | inc42 | O28: 2 | P28: 0 | R28: https://inc42.com/buzz/from-innovaccer-to-beyond-snack-indian-startups-raised-432-mn-this-week/
A29: R250113-bobabhai | B29: Boba Bhai | C29: 45670 | D29: 45658 | E29: 3.46 | F29: 30 | G29: Rs 30 crore | H29: Series A | I29: Early | J29: Consumer Services | K29: Bengaluru | L29: 8i Ventures | M29: 8i Ventures; Titan Capital Winners Fund; Global Growth Capital; DevC; Z47 | N29: entrackr | inc42 | et | O29: 3 | P29: 1.8 | R29: https://entrackr.com/snippets/bubble-tea-brand-boba-bhai-raises-rs-30-cr-in-series-a-round-8614194
A30: R250113-weworkindia | B30: WeWork India | C30: 45670 | D30: 45658 | E30: 57.7 | F30: 500.26 | G30: $57.7 Mn | H30: Undisclosed | I30: Undisclosed | J30: Real Estate Tech | K30: Unknown | N30: inc42 | O30: 1 | P30: 0 | Q30: C04 C05 C07 | R30: https://inc42.com/buzz/from-netradyne-to-foxtale-indian-startups-raised-308-mn-this-week/
A31: R250114-bgauss | B31: BGauss | C31: 45671 | D31: 45658 | E31: 18.598 | F31: 161 | G31: Rs 161 crore | H31: Undisclosed | I31: Undisclosed | J31: Cleantech | K31: Pune | L31: Bharat Value Fund | M31: Bharat Value Fund | N31: entrackr | inc42 | et | O31: 3 | P31: 0 | Q31: C04 | R31: https://entrackr.com/news/ev-two-wheeler-manufacturer-bgauss-raises-rs-161-cr-8620040
A32: R250114-bharatpe | B32: BharatPe | C32: 45671 | D32: 45658 | E32: 17.3 | F32: 149.77 | G32: $17.3 Mn | H32: Debt | I32: Debt | J32: Fintech | K32: Unknown | M32: Neo Wealth; Trifecta Capital | N32: inc42 | O32: 1 | P32: 0 | Q32: C07 | R32: https://inc42.com/buzz/from-netradyne-to-foxtale-indian-startups-raised-308-mn-this-week/
A33: R250114-greenstitch | B33: GreenStitch | C33: 45671 | D33: 45658 | E33: 1.2 | F33: 10.39 | G33: $1.2 million | H33: Seed | I33: Early | J33: Ecommerce | K33: Bengaluru | L33: Equirus InnovateX Fund | M33: Equirus InnovateX Fund; Ivycap Ventures; Warmup Ventures; Zeca Ventures; Pankaj Vermani; Amit Kumar | N33: entrackr | et | O33: 2 | P33: 0 | R33: https://economictimes.indiatimes.com/tech/funding/climate-tech-startup-greenstitch-raises-1-2-million-from-equirus-innovatex-fund-others/articleshow/117237257.cms
A34: R250114-tractorfactory | B34: Tractor Factory | C34: 45671 | D34: 45658 | E34: 0.462 | F34: 4 | G34: Rs 4 crore | H34: Pre-Seed | I34: Early | J34: Ecommerce | K34: Jabalpur | L34: All In Capital | M34: All In Capital; Bharat Founders Fund; DevC; Dhingra Partners Prosperity Trust; Samir Sood; Abhishek Goyal; Aayush Phumbra; Puneet Kumar; Additionally; Steadview Capital | N34: entrackr | inc42 | et | O34: 3 | P34: 8.2 | R34: https://entrackr.com/snippets/tractor-factory-raises-500k-in-pre-seed-round-led-by-all-in-capital-8619966
A35: R250115-eccentricengin | B35: Eccentric | C35: 45672 | D35: 45658 | E35: 5 | F35: 43.21 | G35: $5 million | H35: Pre-Series A | I35: Early | J35: Enterprise Tech | K35: Unknown | L35: Exfinity Venture Partners; Arkam Ventures | M35: Exfinity Venture Partners; Arkam Ventures | N35: entrackr | inc42 | et | O35: 3 | P35: 0 | Q35: C07 | R35: https://entrackr.com/snippets/eccentric-engine-raises-5-mn-in-pre-series-a-round-8622777
A36: R250115-ecozen | B36: Ecozen | C36: 45672 | D36: 45658 | E36: 23 | F36: 198.77 | G36: $23 million | H36: Debt | I36: Debt | J36: Agritech | K36: Pune | M36: Northern Arc Capital Limited; Maanaveeya Development; Finance | N36: entrackr | inc42 | O36: 2 | P36: 0 | R36: https://entrackr.com/news/climate-tech-startup-ecozen-raises-23-mn-in-debt-8623678
A37: R250115-erlysign | B37: ErlySign | C37: 45672 | D37: 45658 | E37: 1.851 | F37: 16 | G37: Rs 16 crore | H37: Pre-Series A | I37: Early | J37: Healthtech | K37: Unknown | L37: Ashish Kacholia | M37: Ashish Kacholia | N37: entrackr | inc42 | O37: 2 | P37: 2.9 | Q37: C07 | R37: https://inc42.com/buzz/from-netradyne-to-foxtale-indian-startups-raised-308-mn-this-week/
A38: R250115-eulermotors | B38: Euler Motors | C38: 45672 | D38: 45658 | E38: 20 | F38: 172.84 | G38: $20 Mn | H38: Debt | I38: Debt | J38: Cleantech | K38: Delhi NCR | N38: inc42 | O38: 1 | P38: 0 | Q38: C05 | R38: https://inc42.com/buzz/from-netradyne-to-foxtale-indian-startups-raised-308-mn-this-week/
A39: R250115-foxtale | B39: Foxtale | C39: 45672 | D39: 45658 | E39: 30 | F39: 259.26 | G39: $30 million | H39: Series C | I39: Growth | J39: Ecommerce | K39: Mumbai | L39: KOSÉ Corporation | M39: KOSÉ Corporation; Panthera Growth Partners; Z47; Kae Capital | N39: entrackr | inc42 | et | O39: 3 | P39: 0 | R39: https://entrackr.com/news/d2c-skincare-brand-foxtale-raises-30-mn-8623443
A40: R250115-orbitaid | B40: OrbitAID | C40: 45672 | D40: 45658 | E40: 1.5 | F40: 12.96 | G40: $1.5 million | H40: Pre-Seed | I40: Early | J40: Deeptech | K40: Chennai | L40: Unicorn India Ventures | M40: Unicorn India Ventures; Tamil Nadu Startup; Innovation Mission; TANSIM | N40: entrackr | inc42 | et | O40: 3 | P40: 0 | R40: https://entrackr.com/snippets/spacetech-startup-orbitaid-raises-15-mn-led-by-unicorn-india-ventures-8622828
A41: R250115-parkmate | B41: ParkMate | C41: 45672 | D41: 45658 | E41: 1.2 | F41: 10.37 | G41: $1.2 million | H41: Undisclosed | I41: Undisclosed | J41: Consumer Services | K41: Delhi NCR | L41: Cactus Partners; Marwah Group Family Office | M41: Cactus Partners; Venture Catalysts; Marwah Group Family Office | N41: entrackr | inc42 | O41: 2 | P41: 0 | Q41: C04 | R41: https://entrackr.com/snippets/cactus-partners-leads-12-mn-round-in-parkmate-8623699
A42: R250115-sarlaaviation | B42: Sarla Aviation | C42: 45672 | D42: 45658 | E42: 10 | F42: 86.42 | G42: $10 million | H42: Series A | I42: Early | J42: Deeptech | K42: Unknown | L42: Accel | M42: Accel; Binny Bansal; Nikhil Kamath; Sriharsha Majety; Abhiraj Singh Bhal; Abhishek Goyal; Ramakant Sharma; Sujeet Kumar; Manish Agarwal; Sandeep Nailwal | N42: entrackr | inc42 | et | O42: 3 | P42: 0 | Q42: C07 | R42: https://entrackr.com/snippets/aerospace-startup-sarla-aviation-raises-10-mn-led-by-accel-8622762
A43: R250115-sukoonunlimite | B43: Sukoon Unlimited | C43: 45672 | D43: 45658 | E43: 0.43 | F43: 3.72 | G43: $430K | H43: Pre-Seed | I43: Early | J43: Consumer Services | K43: Unknown | M43: Anchorage Capital Partners; Vinay Jain; Manish Dureja; Rahul Dash; Prantik Mazumdar; Neeraj Sagar; Sudhir Kamath | N43: entrackr | inc42 | O43: 2 | P43: 0 | Q43: C07 | R43: https://entrackr.com/snippets/agetech-startup-sukoon-unlimited-raises-pre-seed-round-8622991
A44: R250115-tyreplex | B44: TyrePlex | C44: 45672 | D44: 45658 | E44: 2.314 | F44: 20 | G44: Rs 20 crore | H44: Undisclosed | I44: Undisclosed | J44: Ecommerce | K44: Unknown | L44: PeerCapital | M44: PeerCapital; Titan Capital Winners Fund; Sattva Family Office; 100Unicorns | N44: entrackr | inc42 | O44: 2 | P44: 3.7 | Q44: C04 C07 | R44: https://entrackr.com/snippets/tyreplex-raises-rs-20-cr-from-peercapital-titan-capital-winners-fund-others-8623233
A45: R250116-astrosureai | B45: AstroSure | C45: 45673 | D45: 45658 | E45: 6 | F45: 51.95 | G45: $6 million | H45: Seed | I45: Early | J45: Consumer Services | K45: Unknown | L45: Pradeep Dadha | M45: Pradeep Dadha | N45: entrackr | inc42 | O45: 2 | P45: 0 | Q45: C07 | R45: https://entrackr.com/snippets/astrosureai-raises-6-mn-in-seed-round-8626771
A46: R250116-constelli | B46: Constelli | C46: 45673 | D46: 45658 | E46: 3 | F46: 25.97 | G46: $3 million | H46: Pre-Series A | I46: Early | J46: Deeptech | K46: Hyderabad | L46: Pravega Ventures | M46: Pravega Ventures | N46: entrackr | inc42 | et | O46: 3 | P46: 0 | R46: https://economictimes.indiatimes.com/tech/funding/defence-tech-startup-constelli-raises-3-million-in-pre-series-a-round-led-by-pravega-ventures/articleshow/117304142.cms
A47: R250116-emiza | B47: Emiza | C47: 45673 | D47: 45658 | E47: 5.775 | F47: 50 | G47: Rs 50 crore | H47: Undisclosed | I47: Undisclosed | J47: Logistics | K47: Mumbai | L47: Evolvence India | M47: Evolvence India; Mirabilis Investment | N47: entrackr | O47: 1 | P47: 0 | Q47: C04 | R47: https://entrackr.com/exclusive/exclusive-emiza-supply-chain-kicks-off-new-funding-round-8625857
A48: R250116-fambo | B48: Fambo | C48: 45673 | D48: 45658 | E48: 2.426 | F48: 21 | G48: Rs 21 crore | H48: Seed | I48: Early | J48: Agritech | K48: Delhi NCR | L48: EV2 Ventures | M48: EV2 Ventures; Rajesh Sawhney | N48: entrackr | inc42 | O48: 2 | P48: 15.5 | Q48: C15 C18 | R48: https://entrackr.com/snippets/foodtech-startup-fambo-raises-rs-21-cr-in-pre-series-a-funding-8626412
A49: R250116-houseofchikank | B49: House of Chikankari | C49: 45673 | D49: 45658 | E49: 0.462 | F49: 4 | G49: Rs 4 crore | H49: Seed | I49: Early | J49: Ecommerce | K49: Delhi NCR | N49: entrackr | O49: 1 | P49: 0 | Q49: C05 | R49: https://entrackr.com/snippets/house-of-chikankari-bags-rs-4-cr-in-seed-round-8625846
A50: R250116-kisaansay | B50: KisaanSay | C50: 45673 | D50: 45658 | E50: 2 | F50: 17.32 | G50: $2 million | H50: Pre-Seed | I50: Early | J50: Ecommerce | K50: Delhi NCR | L50: Jungle Ventures through First Cheque@Jungle | M50: Jungle Ventures through First Cheque@Jungle | N50: entrackr | O50: 1 | P50: 0 | R50: https://entrackr.com/snippets/kisaansay-raises-2-mn-in-pre-seed-round-led-by-jungle-ventures-8625838
A51: R250116-motorfloor | B51: Motorfloor | C51: 45673 | D51: 45658 | H51: Pre-Seed | I51: Early | J51: Unclassified | K51: Bhubaneswar | M51: PointOne Capital | N51: entrackr | O51: 1 | Q51: C03 C06 | R51: https://entrackr.com/snippets/autotech-startup-motorfloor-raises-pre-seed-round-8626200
A52: R250116-wevois | B52: WeVOIS | C52: 45673 | D52: 45658 | E52: 4.158 | F52: 36 | G52: Rs 36 crore | H52: Series A | I52: Early | J52: Cleantech | K52: Unknown | L52: Negen Capital; Vyom Wealth | M52: Negen Capital; Vyom Wealth; Venture Catalysts; SN Capital; Warmup Ventures; Marsshot Ventures | N52: entrackr | inc42 | O52: 2 | P52: 1 | Q52: C07 | R52: https://entrackr.com/snippets/wevois-raises-rs-36-cr-in-series-a-round-from-negen-capital-8626156
A53: R250116-zerocircle | B53: Zerocircle | C53: 45673 | D53: 45658 | E53: 2.31 | F53: 20 | G53: Rs 20 crore | H53: Undisclosed | I53: Undisclosed | J53: Cleantech | K53: Pune | L53: Rainmatter | M53: Rainmatter; VC Grid; 7th Gen Ventures | N53: entrackr | et | O53: 2 | P53: 0 | Q53: C04 | R53: https://entrackr.com/snippets/biotech-startup-zerocircle-raises-rs-20-cr-led-by-rainmatter-8626169
A54: R250122-namdevfinvest | B54: Namdev Finvest | C54: 45673 | D54: 45658 | E54: 38 | F54: 329 | G54: $38 Mn | H54: Debt | I54: Debt | J54: Fintech | K54: Jaipur | M54: Developing World Markets; BlueOrchard; Mirova | N54: inc42 | vccircle | O54: 2 | P54: 0 | R54: https://www.vccircle.com/majinvest-bii-backed-namdev-finvest-pushes-back-fundraising-plan
A55: R250117-boltearth | B55: Bolt.Earth | C55: 45674 | D55: 45658 | E55: 5 | F55: 43.31 | G55: $5 Mn | H55: Series A | I55: Early | J55: Cleantech | K55: Unknown | L55: Version One Ventures | M55: Version One Ventures; Union Square Ventures; Prime Venture Partners | N55: inc42 | O55: 1 | P55: 0 | Q55: C07 | R55: https://inc42.com/buzz/from-netradyne-to-foxtale-indian-startups-raised-308-mn-this-week/
A56: R250117-captainfresh | B56: Captain Fresh | C56: 45674 | D56: 45658 | E56: 2.3 | F56: 19.92 | G56: $2.3 Mn | H56: Debt | I56: Debt | J56: Agritech | K56: Bengaluru | L56: VentureSoul Partners | M56: VentureSoul Partners | N56: inc42 | O56: 1 | P56: 0 | R56: https://inc42.com/buzz/from-netradyne-to-foxtale-indian-startups-raised-308-mn-this-week/
A57: R250117-catalyxspace | B57: Catalyx Space | C57: 45674 | D57: 45658 | E57: 1.7 | F57: 14.73 | G57: $1.7 Mn | H57: Pre-Seed | I57: Early | J57: Deeptech | K57: Unknown | L57: HF0 Residency | M57: HF0 Residency | N57: inc42 | O57: 1 | P57: 0 | Q57: C07 | R57: https://inc42.com/buzz/from-netradyne-to-foxtale-indian-startups-raised-308-mn-this-week/
A58: R250117-netradyne | B58: Netradyne | C58: 45674 | D58: 45658 | E58: 90 | F58: 779.58 | G58: $90 million | H58: Series D | I58: Late | J58: Logistics | K58: Unknown | L58: Point72 Private Investments | M58: Point72 Private Investments; Qualcomm Ventures; Pavilion Capital | N58: entrackr | inc42 | et | O58: 3 | P58: 0 | Q58: C07 | R58: https://entrackr.com/news/reliance-and-softbank-backed-netradyne-raises-90-mn-in-series-d-8629017
A59: R250117-trezix | B59: TreZix | C59: 45674 | D59: 45658 | E59: 2 | F59: 17.32 | G59: $2 Mn | H59: Seed | I59: Early | J59: Enterprise Tech | K59: Unknown | L59: Morphosis Venture Capital; Pentathlon Ventures | M59: Morphosis Venture Capital; Pentathlon Ventures | N59: inc42 | O59: 1 | P59: 0 | Q59: C07 | R59: https://inc42.com/buzz/from-netradyne-to-foxtale-indian-startups-raised-308-mn-this-week/
A60: R250118-gridos | B60: Grid OS | C60: 45675 | D60: 45658 | E60: 0.5 | F60: 4.33 | G60: $500,000 | H60: Undisclosed | I60: Undisclosed | J60: Unclassified | K60: Delhi NCR | L60: Anupam Mittal; All In Capital | M60: Anupam Mittal; All In Capital; Pravin Jadhav | N60: et | O60: 1 | P60: 0 | Q60: C04 C06 | R60: https://economictimes.indiatimes.com/tech/funding/electronics-manufacturing-startup-grid-os-raises-500000-in-round-led-by-anupam-mittal-all-in-capital/articleshow/117352343.cms
A61: R250120-bprhub | B61: BPR Hub | C61: 45677 | D61: 45658 | E61: 2.6 | F61: 22.5 | G61: $2.6 million | H61: Seed | I61: Early | J61: Unclassified | K61: Bengaluru | L61: Accel; Kae Capital | M61: Accel; Kae Capital | N61: entrackr | et | O61: 2 | P61: 0 | Q61: C06 | R61: https://entrackr.com/snippets/bpr-hub-raises-26-mn-led-by-accel-and-kae-capital-8638299
A62: R250120-burmaburma | B62: Burma Burma | C62: 45677 | D62: 45658 | E62: 3 | F62: 25.96 | G62: $3 Mn | H62: Undisclosed | I62: Undisclosed | J62: Consumer Services | K62: Unknown | M62: Negen Capital; NV Alpha Fund Management | N62: inc42 | O62: 1 | P62: 0 | Q62: C04 C07 | R62: https://inc42.com/buzz/from-infra-market-to-arisinfra-indian-startups-raised-275-mn-this-week/
A63: R250120-kisankonnect | B63: KisanKonnect | C63: 45677 | D63: 45658 | E63: 4.5 | F63: 38.94 | G63: $4.5 million | H63: Series A | I63: Early | J63: Agritech | K63: Unknown | L63: Mistry Ventures | M63: Mistry Ventures; Brand Capital; VC-Grid; Vishwang Desai; Shilpa Shetty | N63: entrackr | inc42 | O63: 2 | P63: 0 | Q63: C07 | R63: https://entrackr.com/snippets/mistry-ventures-leads-45-mn-round-in-kisankonnect-8637095
A64: R250120-krvvy | B64: Krvvy | C64: 45677 | D64: 45658 | E64: 0.705 | F64: 6.1 | G64: Rs 6.1 crore | H64: Pre-Seed | I64: Early | J64: Ecommerce | K64: Unknown | L64: Titan Capital; All In Capital | M64: Titan Capital; All In Capital; Nikita Gupta; Emmanuel Suraj; Anuj Jain; Anubhav Arora; Anubhav Jain | N64: entrackr | et | O64: 2 | P64: 0 | Q64: C07 | R64: https://entrackr.com/snippets/krvvy-raises-rs-61-cr-from-titan-capital-and-all-in-capital-8636581
A65: R250120-nazara | B65: Nazara | C65: 45677 | D65: 45658 | E65: 57.199 | F65: 495 | G65: Rs 495 crore | H65: Undisclosed | I65: Undisclosed | J65: Media & Entertainment | K65: Outside India | L65: Axana Estates LLP; Arpit Khandelwal; Mithun Sacheti | M65: Axana Estates LLP; Arpit Khandelwal; Mithun Sacheti | N65: entrackr | et | O65: 2 | P65: 0 | Q65: C04 C17 | R65: https://entrackr.com/news/nazara-raises-rs-495-cr-from-arpit-khandelwal-and-mithun-sacheti-led-axana-estates-8637532
A66: R250120-prantaesolutio | B66: Prantae Solutions | C66: 45677 | D66: 45658 | E66: 0.578 | F66: 5 | G66: Rs 5 crore | H66: Seed | I66: Early | J66: Healthtech | K66: Bhubaneswar | L66: IAN Group | M66: IAN Group; Samir Kalia; Deepank Kumar; Nitin Zamre | N66: entrackr | inc42 | O66: 2 | P66: 0.4 | R66: https://entrackr.com/snippets/prantae-solutions-saises-seed-round-from-ian-group-8637291
A67: R250120-procureyard | B67: ProcureYard | C67: 45677 | D67: 45658 | E67: 1.72 | F67: 14.88 | G67: $1.72 million | H67: Seed | I67: Early | J67: Ecommerce | K67: Unknown | L67: Powerhouse Ventures | M67: Powerhouse Ventures; Java Capital; 2am VC; Abhishek Goyal; Rajesh Sawhney; Tracxn; GSF | N67: entrackr | inc42 | O67: 2 | P67: 1.2 | Q67: C07 | R67: https://entrackr.com/snippets/procureyard-raises-172-mn-in-seed-round-8636600
A68: R250121-chelviescoffee | B68: Chelvies Coffee | C68: 45678 | D68: 45658 | E68: 1 | F68: 8.66 | G68: $1 million | H68: Pre-Series A | I68: Early | J68: Consumer Services | K68: Delhi NCR | L68: Endurance Capital | M68: Endurance Capital | N68: entrackr | inc42 | O68: 2 | P68: 0 | R68: https://entrackr.com/snippets/chelvies-coffee-raises-1-mn-in-pre-series-a-round-8640133
A69: R250121-joyspoon | B69: JoySpoon | C69: 45678 | D69: 45658 | E69: 0.065 | F69: 0.56 | G69: Rs 56 lakhs | H69: Seed | I69: Early | J69: Ecommerce | K69: Unknown | L69: Dishit Nathwani | M69: Dishit Nathwani; Prateek Toshniwal; Abhinav Jain; Ankit Jain; CFOs at CoinDCX; PharmEasy | N69: entrackr | inc42 | O69: 2 | P69: 224.7 | Q69: C07 C11 C15 | R69: https://entrackr.com/snippets/joyspoon-raises-more-money-in-seed-round-8639852
A70: R250121-postudio | B70: Postudio | C70: 45678 | D70: 45658 | E70: 1 | F70: 8.66 | G70: $1 million | H70: Pre-Seed | I70: Early | J70: Enterprise Tech | K70: Unknown | L70: Audacity Venture Capital | M70: Audacity Venture Capital | N70: entrackr | et | O70: 2 | P70: 0 | Q70: C07 | R70: https://entrackr.com/snippets/postudio-raises-1-mn-in-pre-seed-funding-8639868
A71: R250121-snabbit | B71: Snabbit | C71: 45678 | D71: 45658 | E71: 5.5 | F71: 47.63 | G71: $5.5 million | H71: Series A | I71: Early | J71: Consumer Services | K71: Mumbai | L71: Elevation Capital | M71: Elevation Capital; Nexus Venture Partners; Vidit Aatrey; Sanjeev Barnwal; Gaurav Munjal; Niraj Singh | N71: entrackr | inc42 | et | O71: 3 | P71: 0 | R71: https://entrackr.com/snippets/quick-service-app-snabbit-raises-55-mn-led-by-elevation-and-nexus-8639619
A72: R250121-workie | B72: Workie | C72: 45678 | D72: 45658 | E72: 1.501 | F72: 13 | G72: Rs 13 crore | H72: Undisclosed | I72: Undisclosed | J72: Real Estate Tech | K72: Indore | L72: Sunil Singhania Family Office; NAV Capital; Raman Roy; Dharmendra Jain; Gaurav Singhvi; Sunil Singhvi | M72: NAV Capital; Raman Roy; Dharmendra Jain; Gaurav Singhvi; Sunil Singhvi; Sunil Singhania Family Office | N72: entrackr | inc42 | O72: 2 | P72: 0.1 | Q72: C04 | R72: https://inc42.com/buzz/from-infra-market-to-arisinfra-indian-startups-raised-275-mn-this-week/
A73: R250122-cancrie | B73: Cancrie | C73: 45679 | D73: 45658 | E73: 1.2 | F73: 10.37 | G73: $1.2 million | H73: Seed | I73: Early | J73: Cleantech | K73: Jaipur | L73: Roots Ventures; Foundation Botnar; Sagana | M73: Roots Ventures; Foundation Botnar; Sagana; IIMA Ventures | N73: entrackr | inc42 | O73: 2 | P73: 0 | R73: https://entrackr.com/snippets/cancrie-raises-12-mn-in-seed-funding-round-8644225
A74: R250122-deconstruct | B74: DeConstruct | C74: 45679 | D74: 45658 | E74: 7.525 | F74: 65 | G74: Rs 65 crore | H74: Undisclosed | I74: Undisclosed | J74: Ecommerce | K74: Unknown | M74: BOLD; V3 Ventures; DSG Consumer Partners; Kalaari Capital; BEENEXT | N74: entrackr | inc42 | O74: 2 | P74: 0.3 | Q74: C04 C07 | R74: https://entrackr.com/news/deconstruct-raises-rs-65-cr-from-loréals-vc-fund-bold-and-others-8643091
A75: R250122-exsure | B75: Exsure | C75: 45679 | D75: 45658 | E75: 0.347 | F75: 3 | G75: Rs 3 crore | H75: Seed | I75: Early | J75: Healthtech | K75: Bhubaneswar | L75: Unicorn India Ventures | M75: Unicorn India Ventures | N75: entrackr | inc42 | O75: 2 | P75: 0.2 | R75: https://entrackr.com/snippets/biotech-startup-exsure-raises-seed-round-led-by-unicorn-india-ventures-8643695
A76: R250122-raazapp | B76: Raaz App | C76: 45679 | D76: 45658 | E76: 1 | F76: 8.64 | G76: $1 million | H76: Pre-Seed | I76: Early | J76: Healthtech | K76: Bengaluru | L76: Fireside Ventures | M76: Fireside Venture; Campus Fund; Altaf Saiyed; Raymond Russell; Vaibhav Domkundwar; Shreyas Kumar; Bhargav Tarpara | N76: entrackr | inc42 | et | O76: 3 | P76: 0 | R76: https://entrackr.com/snippets/healthcare-platform-raaz-app-raises-1-mn-led-by-fireside-ventures-8643414
A77: R250122-spare8 | B77: Spare8 | C77: 45679 | D77: 45658 | H77: Undisclosed | I77: Undisclosed | J77: Fintech | K77: Unknown | M77: Param Agrawal; Rajiv Shastri | N77: inc42 | O77: 1 | Q77: C03 C04 C07 | R77: https://inc42.com/buzz/from-infra-market-to-arisinfra-indian-startups-raised-275-mn-this-week/
A78: R250122-zeelabpharmacy | B78: Zeelab Pharmacy | C78: 45679 | D78: 45658 | E78: 2.4 | F78: 20.73 | G78: $2.4 million | H78: Undisclosed | I78: Undisclosed | J78: Healthtech | K78: Delhi NCR | L78: OTP Ventures | M78: OTP Ventures | N78: entrackr | inc42 | et | O78: 3 | P78: 0 | Q78: C04 | R78: https://entrackr.com/snippets/otp-ventures-leads-24-mn-round-in-zeelab-pharmacy-8643423
A79: R250123-arisinfra | B79: ArisInfra | C79: 45680 | D79: 45658 | E79: 9.3 | F79: 80.39 | G79: $9.3 Mn | H79: Undisclosed | I79: Undisclosed | J79: Ecommerce | K79: Unknown | M79: Vanaja Sundar Iyer; Mukul Mahavir Agrawal; Rishabh Bharatbhai Bagdia | N79: inc42 | O79: 1 | P79: 0 | Q79: C04 C07 | R79: https://inc42.com/buzz/from-infra-market-to-arisinfra-indian-startups-raised-275-mn-this-week/
A80: R250123-arya | B80: Arya.ag | C80: 45680 | D80: 45658 | E80: 30 | F80: 259.32 | G80: $30 Mn | H80: Debt | I80: Debt | J80: Agritech | K80: Delhi NCR | M80: HSBC | N80: inc42 | et | O80: 2 | P80: 0 | R80: https://economictimes.indiatimes.com/tech/funding/agritech-startup-arya-secures-30-million-in-debt-financing/articleshow/117490646.cms
A81: R250123-atimotors | B81: Ati Motors | C81: 45680 | D81: 45658 | E81: 20 | F81: 172.88 | G81: $20 million | H81: Series B | I81: Growth | J81: Deeptech | K81: Bengaluru | L81: Walden Catalyst Ventures; NGP Capital | M81: Walden Catalyst Ventures; NGP Capital; True Ventures; Exfinity Venture Partners; Athera Venture Partners; Blume Ventures | N81: entrackr | inc42 | et | O81: 3 | P81: 0 | R81: https://entrackr.com/news/industrial-robotics-startup-ati-motors-raises-20-mn-in-series-b-round-8646163
A82: R250123-dreamaerospace | B82: Dream Aerospace | C82: 45680 | D82: 45658 | E82: 0.347 | F82: 3 | G82: Rs 3 crore | H82: Pre-Seed | I82: Early | J82: Deeptech | K82: Chennai | L82: Inflection Point Ventures | M82: Inflection Point Ventures | N82: entrackr | inc42 | O82: 2 | P82: 0.3 | R82: https://entrackr.com/snippets/dream-aerospace-raises-rs-3-cr-in-pre-seed-round-8646648
A83: R250123-inframarket | B83: Infra.Market | C83: 45680 | D83: 45658 | E83: 121 | F83: 1045.92 | G83: $121 Mn | H83: Series F | I83: Late | J83: Ecommerce | K83: Mumbai | M83: Tiger Global; Foundamental GmbH; Evolvence; Nikhil Kamath; Ashish Kacholia; Abhijit Pai; Sumeet Kanwar; Nuvama; Capri Global | N83: inc42 | et | O83: 2 | P83: 0 | Q83: C18 | R83: https://economictimes.indiatimes.com/tech/funding/infra-market-secures-rs-1050-crore-in-pre-ipo-funding/articleshow/117486734.cms
A84: R250123-landeed | B84: Landeed | C84: 45680 | D84: 45658 | E84: 5 | F84: 43.22 | G84: $5 million | H84: Undisclosed | I84: Undisclosed | J84: Real Estate Tech | K84: Unknown | L84: 10x Founders Fund | M84: 10x Founders Fund; Oliver Jung; Paradigm Shift; Pioneer Fund; Jeffrey Epstein; Aaron King | N84: entrackr | inc42 | O84: 2 | P84: 0 | Q84: C04 C07 | R84: https://entrackr.com/snippets/y-combinator-backed-landeed-raises-5-mn-8645853
A85: R250123-svastek | B85: SVASTEK | C85: 45680 | D85: 45658 | E85: 0.231 | F85: 2 | G85: Rs 2 crore | H85: Pre-Seed | I85: Early | J85: Healthtech | K85: Delhi NCR | L85: IAN Angel Fund | M85: IAN Angel Fund | N85: entrackr | inc42 | O85: 2 | P85: 0.3 | Q85: C18 | R85: https://entrackr.com/snippets/ian-group-leads-seed-round-in-medtech-startup-svastek-8647043
A86: R250123-vunetsystems | B86: VuNet Systems | C86: 45680 | D86: 45658 | E86: 6.941 | F86: 60 | G86: Rs 60 crore | H86: Series B | I86: Growth | J86: Enterprise Tech | K86: Bengaluru | L86: Pravega Ventures | M86: Pravega Ventures; Mela Ventures; Athera Venture Partners; Dallas Venture Capital; Kotak Securities | N86: entrackr | inc42 | et | vccircle | O86: 4 | P86: 0.6 | R86: https://entrackr.com/snippets/vunet-systems-raises-rs-60-cr-in-series-b-round-8646289
A87: R250124-pipeshift | B87: Pipeshift | C87: 45680 | D87: 45658 | E87: 2.5 | F87: 21.61 | G87: $2.5 million | H87: Seed | I87: Early | J87: Enterprise Tech | K87: Unknown | L87: Y Combinator; SenseAI Ventures | M87: Y Combinator; SenseAI Ventures; Arka Venture Labs; Good News Ventures; Nivesha Ventures; Astir VC; GradCapital; MyAsiaVC; Kulveer Taggar; Umur Cubukcu; Krishna Mehra | N87: entrackr | inc42 | et | O87: 3 | P87: 0 | Q87: C07 | R87: https://economictimes.indiatimes.com/tech/funding/ai-infrastructure-startup-pipeshift-raises-2-5-million-from-y-combinator-others/articleshow/117493444.cms
A88: R250124-capgrid | B88: CapGrid | C88: 45681 | D88: 45658 | E88: 3.3 | F88: 28.47 | G88: $3.3 Mn | H88: Series A | I88: Early | J88: Enterprise Tech | K88: Unknown | M88: Anicut Capital; Nexus Ventures; Axilor Ventures | N88: inc42 | O88: 1 | P88: 0 | Q88: C07 | R88: https://inc42.com/buzz/from-infra-market-to-arisinfra-indian-startups-raised-275-mn-this-week/
A89: R250124-medusabeverage | B89: Medusa | C89: 45681 | D89: 45658 | E89: 6.492 | F89: 56 | G89: Rs 56 crore | H89: Series A | I89: Early | J89: Alcoholic Beverages | K89: Delhi NCR | L89: Amal N. Parikh; Ashwin Kedia | M89: Amal N Parikh; Ashwin Kedia; Ramesh Damani; Crest Opportunities; Nikhil Garg | N89: entrackr | inc42 | O89: 2 | P89: 0.1 | R89: https://entrackr.com/snippets/medusa-beverages-raises-rs-56-cr-in-series-a-funding-8649454
A90: R250127-astrometechnol | B90: Astrome | C90: 45684 | D90: 45658 | E90: 10 | F90: 86.31 | G90: $10 million | H90: Undisclosed | I90: Undisclosed | J90: Deeptech | K90: Unknown | L90: Apollo Global Management | M90: Apollo Global Management; IAN Group | N90: entrackr | inc42 | O90: 2 | P90: 0 | Q90: C04 C07 | R90: https://entrackr.com/news/astrome-technologies-raises-10-mn-led-by-appollo-fund-8658316
A91: R250127-emiza | B91: Emiza | C91: 45684 | D91: 45658 | E91: 11.586 | F91: 100 | G91: Rs 100 crore | H91: Series C | I91: Growth | J91: Logistics | K91: Mumbai | L91: Evolvence India; Mirabilis Investment Trust | M91: Evolvence India; Mirabilis Investment Trust | N91: entrackr | inc42 | O91: 2 | P91: 3.6 | Q91: C09 | R91: https://entrackr.com/snippets/emiza-raises-rs-100-cr-in-series-c-round-8657375
A92: R250127-gericarehealth | B92: Geri Care Health Services | C92: 45684 | D92: 45658 | E92: 12.745 | F92: 110 | G92: Rs 110 crore | H92: Undisclosed | I92: Undisclosed | J92: Healthtech | K92: Chennai | L92: InvAscent | M92: InvAscent | N92: entrackr | O92: 1 | P92: 0 | Q92: C04 | R92: https://entrackr.com/snippets/invascent-leads-13-mn-round-in-geri-care-health-services-8658435
A93: R250127-indulgeglobal | B93: Indulge Global | C93: 45684 | D93: 45658 | E93: 1 | F93: 8.63 | G93: $1 Mn | H93: Undisclosed | I93: Undisclosed | J93: Consumer Services | K93: Unknown | M93: Gautham Pai; Nikhil Shettar | N93: inc42 | O93: 1 | P93: 0 | Q93: C04 C07 | R93: https://inc42.com/buzz/from-leap-to-innov8-indian-startups-raised-196-mn-this-week/
A94: R250127-meesho | B94: Meesho | C94: 45684 | D94: 45658 | E94: 550 | F94: 4747.05 | G94: $550 million | H94: Undisclosed | I94: Undisclosed | J94: Ecommerce | K94: Bengaluru | N94: et | O94: 1 | P94: 0 | Q94: C04 C05 | R94: https://economictimes.indiatimes.com/tech/startups/meesho-closes-550-million-round-moves-nclt-to-shift-domicile/articleshow/117583844.cms
A95: R250127-tracknow | B95: trackNOW | C95: 45684 | D95: 45658 | H95: Undisclosed | I95: Undisclosed | J95: Enterprise Tech | K95: Unknown | L95: Poonawalla Group | M95: Poonawalla Group | N95: inc42 | O95: 1 | Q95: C03 C04 C07 | R95: https://inc42.com/buzz/from-leap-to-innov8-indian-startups-raised-196-mn-this-week/
A96: R250127-voltup | B96: VoltUp | C96: 45684 | D96: 45658 | E96: 8 | F96: 69.05 | G96: $8 million | H96: Seed | I96: Early | J96: Cleantech | K96: Mumbai | L96: EM Impact Capital | M96: EM Impact Capital; HDFC Bank; cKers; Grip Invest; GetVantage | N96: entrackr | inc42 | O96: 2 | P96: 0 | R96: https://entrackr.com/snippets/voltup-raises-8-mn-in-seed-funding-round-8657725
A97: R250128-ambak | B97: Ambak | C97: 45685 | D97: 45658 | E97: 7 | F97: 60.59 | G97: $7 million | H97: Pre-Series A | I97: Early | J97: Fintech | K97: Delhi NCR | L97: Peak XV; Surge | M97: Peak XV; Advantage VC; DeVC; Advantedge VC; Surge; Z47 | N97: entrackr | inc42 | et | O97: 3 | P97: 0 | Q97: C17 | R97: https://entrackr.com/snippets/home-loan-startup-ambak-raises-7-mn-led-by-peak-xv-8661535
A98: R250128-atomicwork | B98: Atomicwork | C98: 45685 | D98: 45658 | E98: 25 | F98: 216.4 | G98: $25 million | H98: Series A | I98: Early | J98: Enterprise Tech | K98: Outside India | L98: Khosla Ventures; Z47 Partners | M98: Khosla Ventures; Z47 Partners; Battery Ventures; Peak XV Partners; Blume Ventures | N98: entrackr | inc42 | et | vccircle | O98: 4 | P98: 0 | R98: https://economictimes.indiatimes.com/tech/funding/saas-startup-atomicwork-raises-25-million-in-round-led-by-khosla-ventures-z47/articleshow/117642788.cms
A99: R250128-bizloan | B99: Bizloan | C99: 45685 | D99: 45658 | E99: 4.043 | F99: 35 | G99: Rs 35 crore | H99: Series A | I99: Early | J99: Fintech | K99: Unknown | L99: Michael & Susan Dell Foundation; BLinC Invest | M99: Michael & Susan Dell Foundation; BLinC Invest | N99: entrackr | inc42 | O99: 2 | P99: 3.9 | Q99: C07 | R99: https://entrackr.com/snippets/nbfc-bizloan-raises-rs-35-cr-in-series-a-funding-8660744
A100: R250128-innov8 | B100: Innov8 | C100: 45685 | D100: 45658 | E100: 13 | F100: 112.53 | G100: $13 million | H100: Undisclosed | I100: Undisclosed | J100: Real Estate Tech | K100: Unknown | L100: Mankind Pharma; Gauri Khan; Rupa Group; Jagruti Dalmia | M100: Mankind Pharma; Gauri Khan; Rupa Group; Jagruti Dalmia | N100: entrackr | inc42 | et | O100: 3 | P100: 2.4 | Q100: C04 C07 | R100: https://entrackr.com/news/oyo-owned-innov8-raises-rs-110-cr-at-rs-1000-cr-valuation-8660332
...

Sheet By Sector
A1: Rounds by sector
A2: PivotTable on the Rounds table. It refreshes when the file opens; drag fields to re-cut it.
B4: Values
A5: Sector | B5: Rounds | C5: Total USD mn | D5: Average USD mn
A6: Ecommerce | B6: 478 | C6: 4180.835 | D6: 9.5671281
A7: Fintech | B7: 238 | C7: 5687.77 | D7: 25.278978
A8: Artificial Intelligence | B8: 216 | C8: 3571.075 | D8: 18.035732
A9: Enterprise Tech | B9: 177 | C9: 2460.343 | D9: 15.002091
A10: Advanced Hardware & Technology | B10: 167 | C10: 1160.449 | D10: 7.4867677
A11: Cleantech | B11: 151 | C11: 2122.735 | D11: 14.639552
A12: Healthtech | B12: 137 | C12: 1640.126 | D12: 12.813484
A13: Consumer Services | B13: 125 | C13: 1274.084 | D13: 11.078991
A14: Media & Entertainment | B14: 64 | C14: 456.963 | D14: 8.4622778
A15: Deeptech | B15: 49 | C15: 206.335 | D15: 4.3901064
A16: Travel Tech | B16: 45 | C16: 590.648 | D16: 13.423818
A17: Agritech | B17: 45 | C17: 470.834 | D17: 10.949628
... A25: Grand Total | B25: 2178 | C25: 28468.859 | D25: 14.142503

Sheet By Stage
A1: Rounds by stage
A2: PivotTable on the Rounds table. It refreshes when the file opens; drag fields to re-cut it.
B4: Values
A5: Stage | B5: Rounds | C5: Total USD mn | D5: Average USD mn
A6: Pre-Seed | B6: 242 | C6: 203.326 | D6: 0.92842922
A7: Seed | B7: 467 | C7: 1702.189 | D7: 3.7826422
A8: Angel | B8: 9 | C8: 4.719 | D8: 0.7865
A9: Pre-Series A | B9: 231 | C9: 569.341 | D9: 2.5762036
A10: Series A | B10: 311 | C10: 3070.803 | D10: 9.9701396
A11: Pre-Series B | B11: 25 | C11: 205.636 | D11: 8.5681667
A12: Series B | B12: 150 | C12: 4126.042 | D12: 27.691557
A13: Pre-Series C | B13: 7 | C13: 77.178 | D13: 11.025429
A14: Series C | B14: 51 | C14: 2431.568 | D14: 48.63136
A15: Series D | B15: 22 | C15: 952.316 | D15: 43.287091
A16: Series E | B16: 11 | C16: 869.889 | D16: 79.080818
A17: Series F | B17: 12 | C17: 1464.217 | D17: 122.01808
... A24: Grand Total | B24: 2178 | C24: 28468.859 | D24: 14.142503

Sheet By City
A1: Rounds by city
A2: PivotTable on the Rounds table. It refreshes when the file opens; drag fields to re-cut it.
B4: Values
A5: City | B5: Rounds | C5: Total USD mn | D5: Average USD mn
A6: Bengaluru | B6: 461 | C6: 6699.193 | D6: 14.755932
A7: Delhi NCR | B7: 283 | C7: 2980.407 | D7: 10.997812
A8: Mumbai | B8: 191 | C8: 4648.204 | D8: 25.261978
A9: Pune | B9: 52 | C9: 347.969 | D9: 7.1014082
A10: Chennai | B10: 52 | C10: 403.913 | D10: 8.07826
A11: Hyderabad | B11: 51 | C11: 560.729 | D11: 10.994686
A12: Ahmedabad | B12: 18 | C12: 156.199 | D12: 9.7624375
A13: Jaipur | B13: 15 | C13: 98.34 | D13: 7.5646154
A14: Kolkata | B14: 8 | C14: 21.031 | D14: 2.628875
A15: Chandigarh | B15: 7 | C15: 25.884 | D15: 3.6977143
A16: Surat | B16: 6 | C16: 38.034 | D16: 7.6068
A17: Bhubaneswar | B17: 5 | C17: 8.333 | D17: 2.08325
... A39: Grand Total | B39: 2178 | C39: 28468.859 | D39: 14.142503

Sheet Checks
A1: The 18 automated checks
A2: Every round is tested on each run. A flag sends the round to a person; nothing is corrected automatically.
A4: ID | B4: Category | C4: Check | D4: Rule | E4: Severity | F4: Rounds checked | G4: Rounds flagged | H4: Share flagged
A5: C01 | B5: Nulls | C5: Company name missing | D5: company is blank | E5: error | F5: 2178 | G5: 0 | H5: 0 | I5: ●
A6: C02 | B6: Nulls | C6: Announcement date missing | D6: announced_date is blank or not a date | E6: error | F6: 2178 | G6: 0 | H6: 0 | I6: ●
A7: C03 | B7: Nulls | C7: Amount undisclosed | D7: no source reports an amount | E7: info | F7: 2178 | G7: 165 | H7: 0.0758 | I7: ●
A8: C04 | B8: Nulls | C8: Stage undisclosed | D8: no source names the round stage | E8: info | F8: 2178 | G8: 527 | H8: 0.242 | I8: ●
A9: C05 | B9: Nulls | C9: No investor named | D9: no source names an investor | E9: info | F9: 2178 | G9: 124 | H9: 0.0569 | I9: ●
A10: C06 | B10: Nulls | C10: Sector unclassified | D10: no sector label in a source table and no keyword match | E10: warning | F10: 2178 | G10: 136 | H10: 0.0624 | I10: ●
A11: C07 | B11: Nulls | C11: City unknown | D11: no report says where the company is based | E11: info | F11: 2178 | G11: 950 | H11: 0.4362 | I11: ●
A12: C08 | B12: Duplicates | C12: Duplicate report | D12: one article URL appears more than once in the source records | E12: error | F12: 2178 | G12: 0 | H12: 0 | I12: ●
A13: C09 | B13: Duplicates | C13: Possible duplicate round | D13: same company has another round within 45 days | E13: warning | F13: 2178 | G13: 29 | H13: 0.0133 | I13: ●
A14: C10 | B14: Validity | C14: Date outside tracking window | D14: announced_date before 2025-01-01 or in the future | E14: error | F14: 2178 | G14: 0 | H14: 0 | I14: ●
A15: C11 | B15: Outliers | C15: Amount outlier for its stage | D15: log10(amount) beyond 1.5 x IQR for the stage (stages with at least 10 amounts) | E15: warning | F15: 2178 | G15: 26 | H15: 0.0119 | I15: ●
A16: C12 | B16: Outliers | C16: Implausible amount | D16: amount below $0.01 Mn or above $2000 Mn | E16: warning | F16: 2178 | G16: 0 | H16: 0 | I16: ●
... A22: C18 | B22: Cross-source | C22: Stage disagreement | D22: two detailed sources state different stages | E22: warning | F22: 2178 | G22: 31 | H22: 0.0142 | I22: ●

Sheet Exceptions
A1: Exceptions: every flag raised by the checks
A2: Filter by Check ID or Severity. The Flags column on the Rounds sheet lists the same IDs per round.
A4: Check ID | B4: Check | C4: Severity | D4: Round ID | E4: Company | F4: Announced | G4: Detail
A5: C03 | B5: Amount undisclosed | C5: info | D5: R250102-klassroom | E5: Klassroom | F5: 45659 | G5: amount not disclosed by any source
A6: C03 | B6: Amount undisclosed | C6: info | D6: R250106-blackcarrot | E6: BlackCarrot | F6: 45663 | G6: amount not disclosed by any source
A7: C03 | B7: Amount undisclosed | C7: info | D7: R250107-bodmastechnolo | E7: Bodmas Technologies | F7: 45664 | G7: amount not disclosed by any source
A8: C03 | B8: Amount undisclosed | C8: info | D8: R250109-integrishealth | E8: Integris Health | F8: 45666 | G8: amount not disclosed by any source
A9: C03 | B9: Amount undisclosed | C9: info | D9: R250109-revivo | E9: Revivo | F9: 45666 | G9: amount not disclosed by any source
A10: C03 | B10: Amount undisclosed | C10: info | D10: R250116-motorfloor | E10: Motorfloor | F10: 45673 | G10: amount not disclosed by any source
A11: C03 | B11: Amount undisclosed | C11: info | D11: R250122-spare8 | E11: Spare8 | F11: 45679 | G11: amount not disclosed by any source
A12: C03 | B12: Amount undisclosed | C12: info | D12: R250127-tracknow | E12: trackNOW | F12: 45684 | G12: amount not disclosed by any source
A13: C03 | B13: Amount undisclosed | C13: info | D13: R250129-manastuspace | E13: Manastu Space | F13: 45686 | G13: amount not disclosed by any source
A14: C03 | B14: Amount undisclosed | C14: info | D14: R250203-builditindia | E14: BuilditIndia | F14: 45691 | G14: amount not disclosed by any source
A15: C03 | B15: Amount undisclosed | C15: info | D15: R250203-curefoods | E15: Curefoods | F15: 45691 | G15: amount not disclosed by any source
A16: C03 | B16: Amount undisclosed | C16: info | D16: R250204-coluxe | E16: COLUXE | F16: 45692 | G16: amount not disclosed by any source
... A2137: C18 | B2137: Stage disagreement | C2137: warning | D2137: R260818-rezolv | E2137: Rezolv | F2137: 46252 | G2137: entrackr: Series A; et: Debt; inc42: Series A

Sheet Source rules
A1: Source of truth, field by field
A2: When sources disagree, these rules decide what goes on the Rounds sheet. The disagreement is still flagged.
A4: Field | B4: Source-of-truth rule | C4: Why
A5: Company | B5: The spelling most reports agree on, compared without case or punctuation. Ties go to the Inc42 deal table, then Entrackr, then ET. | C5: Typos differ by source; the spelling several sources share is the safest.
A6: Announced | B6: The earliest publication date among the reports of the round. | C6: Later reports are follow-ups. The first report is closest to the announcement.
A7: Amount (as reported) | B7: The first source that states an amount, in this order: Entrackr, Inc42, ET, VCCircle. Every other figure is kept and compared, never averaged. | C7: Entrackr quotes the announcement currency and usually the dollar equivalent beside it. Inc42 converts everything to dollars. ET often reports a round before its final size is known. VCCircle is a headline only.
A8: Amount (USD mn) | B8: Dollars as stated when the chosen source reports in dollars. Rupee figures are converted at the ECB reference rate for the announcement date. | C8: One published rate per day makes every conversion reproducible.
A9: Amount (INR cr) | B9: Rupees as stated when the chosen source reports in rupees, otherwise converted at the same rate. | C9: Kept beside the dollar figure so either can be checked against the source.
A10: Stage | B10: The first source that names a stage: Inc42 table, Entrackr, ET, VCCircle. | C10: The Inc42 table has a dedicated round-type column. The others are read from prose.
A11: Lead investors / Investors | B11: Every investor named by Inc42, Entrackr or ET, each listed once. | C11: Sources name different subsets of a syndicate, so the union is the fullest list.
A12: Sector | B12: The Inc42 table's sector, with spelling variants merged. If Inc42 did not list the round: the sector Inc42 gave the same company in another round, else a keyword rule on the article's description of the company. Otherwise Unclassified. | C12: One taxonomy for all rounds. The basis is recorded per round in rounds.csv.
A13: City | B13: The city an Entrackr or ET article says the company is based in. If no report of this round says so, the city from another round of the same company. Otherwise Unknown. | C13: Only stated locations are used. Nothing is filled in from memory.
A14: Sources | B14: Every source with a matched report. A VCCircle headline can confirm a round but never creates one. | C14: A company name read from a URL is too rough to establish a round on its own.

Sheet Reports
A1: Source reports matched to a round
A2: One row per article, table row or headline. Amounts are exactly as each source gave them.
A4: Record ID | B4: Round ID | C4: Source | D4: Published | E4: Company in report | F4: Amount as reported | G4: INR cr | H4: USD mn | I4: Stage | J4: Lead investors | K4: Link
A5: INC-20250104-01 | B5: R250102-ayefinance | C5: Inc42 | D5: 45659 | E5: Aye Finance | F5: $12.8 Mn | H5: 12.8 | I5: Debt | K5: https://inc42.com/buzz/from-aye-finance-to-klassroom-indian-startups-raised-14-mn-this-week/
A6: ENT-8584928 | B6: R250102-cargofl | C6: Entrackr | D6: 45659 | E6: CargoFL | F6: Rs 6.75 crore | G6: 6.75 | I6: Seed | J6: YourNest Venture Capital | K6: https://entrackr.com/snippets/cargofl-raises-seed-funding-round-8584928
A7: INC-20250104-02 | B7: R250102-cargofl | C7: Inc42 | D7: 45659 | E7: CargoFL | F7: $787K | H7: 0.787 | I7: Seed | J7: YourNest Venture Capital | K7: https://inc42.com/buzz/from-aye-finance-to-klassroom-indian-startups-raised-14-mn-this-week/
A8: INC-20250104-04 | B8: R250102-klassroom | C8: Inc42 | D8: 45659 | E8: Klassroom | I8: Pre-Series A | K8: https://inc42.com/buzz/from-aye-finance-to-klassroom-indian-startups-raised-14-mn-this-week/
A9: ENT-8591029 | B9: R250104-oyo | C9: Entrackr | D9: 45661 | E9: Oyo | F9: Rs 550 crore | G9: 550 | H9: 65 | I9: Undisclosed | K9: https://entrackr.com/news/oyo-raises-65-mn-from-ritesh-agarwals-redsprig-innovation-8591029
A10: INC-20250111-02 | B10: R250104-oyo | C10: Inc42 | D10: 45662 | E10: OYO | F10: $65 Mn | H10: 65 | I10: Undisclosed | J10: Redsprig Innovation Partners | K10: https://inc42.com/buzz/from-innovaccer-to-beyond-snack-indian-startups-raised-432-mn-this-week/
A11: INC-20250111-18 | B11: R250106-blackcarrot | C11: Inc42 | D11: 45663 | E11: BlackCarrot | I11: Seed | J11: Circle | K11: https://inc42.com/buzz/from-innovaccer-to-beyond-snack-indian-startups-raised-432-mn-this-week/
A12: ENT-8594981 | B12: R250106-consintai | C12: Entrackr | D12: 45663 | E12: Consint.AI | F12: Rs 5 crore | G12: 5 | I12: Seed | J12: Equanimity Ventures; Seafund | K12: https://entrackr.com/snippets/genai-startup-consintai-raises-rs-5-cr-in-seed-round-8594981
A13: ET-117009532 | B13: R250106-consintai | C13: The Economic Times | D13: 45664 | E13: Consint AI | F13: Rs 5 crore | G13: 5 | I13: Undisclosed | K13: https://economictimes.indiatimes.com/tech/funding/healthtech-startup-consint-ai-raises-rs-5-crore/articleshow/117009532.cms
A14: ENT-8594970 | B14: R250106-spintly | C14: Entrackr | D14: 45663 | E14: Spintly | F14: Rs 3.5 crore | G14: 3.5 | I14: Seed | J14: Spyre VC; Chakra Growth Fund; Alumni Ventures; Doctor Technology | K14: https://entrackr.com/snippets/proptech-startup-spintly-raises-rs-35-cr-in-extended-seed-round-8594970
A15: INC-20250111-17 | B15: R250106-spintly | C15: Inc42 | D15: 45663 | E15: Spintly | F15: $407K | H15: 0.407 | I15: Seed | K15: https://inc42.com/buzz/from-innovaccer-to-beyond-snack-indian-startups-raised-432-mn-this-week/
A16: INC-20250111-19 | B16: R250107-bodmastechnolo | C16: Inc42 | D16: 45664 | E16: Bodmas Technologies | I16: Undisclosed | K16: https://inc42.com/buzz/from-innovaccer-to-beyond-snack-indian-startups-raised-432-mn-this-week/
A17: ENT-8598190 | B17: R250107-emoenergy | C17: Entrackr | D17: 45664 | E17: EMO Energy | F17: $6.2 million | H17: 6.2 | I17: Series A | J17: Subhkam Ventures; Transition VC | K17: https://entrackr.com/snippets/emo-energy-raises-62-mn-in-series-a-round-8598190
A18: ET-117002145 | B18: R250107-emoenergy | C18: The Economic Times | D18: 45664 | E18: Emo Energy | F18: $6.2 million | H18: 6.2 | I18: Undisclosed | J18: Subhkam Ventures | K18: https://economictimes.indiatimes.com/tech/funding/subhkam-ventures-leads-6-2-million-round-in-emo-energy/articleshow/117002145.cms
A19: INC-20250111-06 | B19: R250107-emoenergy | C19: Inc42 | D19: 45664 | E19: EMO Energy | F19: $6.2 Mn | H19: 6.2 | I19: Series A | J19: Subhkam Ventures | K19: https://inc42.com/buzz/from-innovaccer-to-beyond-snack-indian-startups-raised-432-mn-this-week/
A20: ENT-8598246 | B20: R250107-kibisports | C20: Entrackr | D20: 45664 | E20: KIBI Sports | F20: $100,000 | H20: 0.1 | I20: Pre-Seed | K20: https://entrackr.com/snippets/kibi-sports-raises-100k-in-pre-seed-funding-8598246
A21: ENT-8597800 | B21: R250107-moonrider | C21: Entrackr | D21: 45664 | E21: Moonrider | F21: $2.2 million | G21: 19 | H21: 2.2 | I21: Seed | J21: Micelio Technology Fund | K21: https://entrackr.com/snippets/electric-tractor-startup-moonrider-raises-22-mn-in-seed-round-8597800
A22: ET-117028244 | B22: R250107-moonrider | C22: The Economic Times | D22: 45664 | E22: Moonrider | F22: $2.2 million | G22: 19 | H22: 2.2 | I22: Undisclosed | J22: Micelio Technology Fund | K22: https://economictimes.indiatimes.com/tech/funding/electric-tractor-technology-startup-moonrider-raises-2-2-million/articleshow/117028244.cms
A23: INC-20250111-13 | B23: R250107-moonrider | C23: Inc42 | D23: 45665 | E23: Moonrider | F23: $2.2 Mn | H23: 2.2 | I23: Seed | J23: Micelio Fund | K23: https://inc42.com/buzz/from-innovaccer-to-beyond-snack-indian-startups-raised-432-mn-this-week/
A24: ENT-8598547 | B24: R250107-obenelectric | C24: Entrackr | D24: 45664 | E24: Oben Electric | F24: Rs 50 crore | G24: 50 | H24: 6 | I24: Series A | K24: https://entrackr.com/snippets/oben-electric-raises-6-mn-in-series-a-8598547
A25: INC-20250111-07 | B25: R250107-obenelectric | C25: Inc42 | D25: 45664 | E25: Oben Electric | F25: $5.8 Mn | H25: 5.8 | I25: Series A | K25: https://inc42.com/buzz/from-innovaccer-to-beyond-snack-indian-startups-raised-432-mn-this-week/
A26: INC-20250111-14 | B26: R250107-pratilipi | C26: Inc42 | D26: 45664 | E26: Pratilipi | F26: $1.2 Mn | H26: 1.2 | I26: Undisclosed | J26: Alteria Capital | K26: https://inc42.com/buzz/from-innovaccer-to-beyond-snack-indian-startups-raised-432-mn-this-week/
A27: ET-117013023 | B27: R250107-vehanttechnolo | C27: The Economic Times | D27: 45664 | E27: Vehant Technologies | F27: $9 million | G27: 77 | H27: 9 | I27: Debt | K27: https://economictimes.indiatimes.com/tech/funding/vehant-technologies-raises-9-million-from-true-north-through-ncds-plans-ipo-by-2026/articleshow/117013023.cms
A28: ENT-8601401 | B28: R250107-vehanttechnolo | C28: Entrackr | D28: 45665 | E28: Vehant Technologies | F28: $9 million | G28: 75 | H28: 9 | I28: Undisclosed | K28: https://entrackr.com/snippets/vehant-technologies-raises-9-mn-from-true-north-8601401
A29: ENT-8598758 | B29: R250107-zoplar | C29: Entrackr | D29: 45664 | E29: Zoplar | F29: $3.4 million | H29: 3.4 | I29: Series A | J29: Blume Ventures | K29: https://entrackr.com/snippets/blume-ventures-leads-34-mn-round-in-zoplar-8598758
A30: INC-20250111-12 | B30: R250107-zoplar | C30: Inc42 | D30: 45664 | E30: Zoplar | F30: $3.4 Mn | H30: 3.4 | I30: Series A | J30: Blume Ventures | K30: https://inc42.com/buzz/from-innovaccer-to-beyond-snack-indian-startups-raised-432-mn-this-week/
A31: ENT-8602138 | B31: R250108-brainsightai | C31: Entrackr | D31: 45665 | E31: BrainSight AI | F31: $5 million | H31: 5 | I31: Pre-Series A | J31: IAN Alpha Fund; Silver Needle | K31: https://entrackr.com/snippets/neuroscience-startup-brainsight-ai-raises-5-mn-8602138
A32: ET-117059845 | B32: R250108-brainsightai | C32: The Economic Times | D32: 45665 | E32: BrainSightAI | F32: $5 million | H32: 5 | I32: Pre-Series A | J32: IAN Alpha Fund | K32: https://economictimes.indiatimes.com/tech/funding/neuroscience-startup-brainsightai-raises-5-million-from-ian-alpha-fund-others/articleshow/117059845.cms
A33: INC-20250111-09 | B33: R250108-brainsightai | C33: Inc42 | D33: 45665 | E33: BrainSinghtAI | F33: $5 Mn | H33: 5 | I33: Pre-Series A | J33: IAN Alpha Fund | K33: https://inc42.com/buzz/from-innovaccer-to-beyond-snack-indian-startups-raised-432-mn-this-week/
A34: ENT-8601862 | B34: R250108-hbits | C34: Entrackr | D34: 45665 | E34: hBits | F34: Rs 40 crore | G34: 40 | I34: Series A | K34: https://entrackr.com/snippets/proptech-startup-hbits-raises-rs-40-cr-in-series-a-8601862
A35: INC-20250111-10 | B35: R250108-hbits | C35: Inc42 | D35: 45665 | E35: hBits | F35: $4.6 Mn | H35: 4.6 | I35: Series A | J35: Capricon Realty | K35: https://inc42.com/buzz/from-innovaccer-to-beyond-snack-indian-startups-raised-432-mn-this-week/
A36: ENT-8600516 | B36: R250108-rasluxuryskinc | C36: Entrackr | D36: 45665 | E36: RAS Luxury Skincare | F36: $5 million | H36: 5 | I36: Series A | J36: Unilever Ventures | K36: https://entrackr.com/snippets/ras-luxury-skincare-raises-5-mn-led-by-unilever-ventures-8600516
A37: ET-117033168 | B37: R250108-rasluxuryskinc | C37: The Economic Times | D37: 45665 | E37: RAS Luxury Skincare | F37: $5 million | H37: 5 | I37: Undisclosed | J37: Unilever Ventures; Unilever | K37: https://economictimes.indiatimes.com/tech/funding/beauty-brand-ras-luxury-skincare-raises-5-million-from-unilever-ventures-others/articleshow/117033168.cms
A38: INC-20250111-08 | B38: R250108-rasluxuryskinc | C38: Inc42 | D38: 45665 | E38: RAS Luxury | F38: $5 Mn | H38: 5 | I38: Series A | J38: Unilever Ventures | K38: https://inc42.com/buzz/from-innovaccer-to-beyond-snack-indian-startups-raised-432-mn-this-week/
A39: ENT-8604226 | B39: R250109-beyondsnack | C39: Entrackr | D39: 45666 | E39: Beyond Snack | F39: $8.3 million | H39: 8.3 | I39: Series A | J39: 12 Flags Group | K39: https://entrackr.com/snippets/beyond-snack-raises-83-mn-in-series-a-round-8604226
A40: ET-117059037 | B40: R250109-beyondsnack | C40: The Economic Times | D40: 45666 | E40: Beyond Snack | F40: $8.3 million | H40: 8.3 | I40: Undisclosed | J40: 12 Flags Group | K40: https://economictimes.indiatimes.com/tech/funding/banana-chips-brand-beyond-snack-bags-8-3-million-in-round-led-by-12-flags-group/articleshow/117059037.cms
A41: INC-20250111-05 | B41: R250109-beyondsnack | C41: Inc42 | D41: 45666 | E41: Beyond Snack | F41: $8.3 Mn | H41: 8.3 | I41: Series A | J41: 12 Flags Group | K41: https://inc42.com/buzz/from-innovaccer-to-beyond-snack-indian-startups-raised-432-mn-this-week/
A42: VCC-535f3dc4e0 | B42: R250109-beyondsnack | C42: VCCircle | D42: 45666 | E42: beyondsnack | F42: $ 8.3 million | H42: 8.3 | I42: Pre-Seed | K42: https://www.vccircle.com/beyondsnack-bags-8-3-mn-dr-doodley-revivo-get-pre-seed-cheques
A43: ENT-8605812 | B43: R250109-grayquest | C43: Entrackr | D43: 45666 | E43: GrayQuest | F43: Rs 80 crore | G43: 80 | H43: 9.3 | I43: Series B | K43: https://entrackr.com/news/grayquest-raises-93-mn-from-iifl-fintech-fund-claypond-and-pravega-8605812
A44: ET-117088951 | B44: R250109-grayquest | C44: The Economic Times | D44: 45666 | E44: GrayQuest | F44: Rs 80 crore | G44: 80 | H44: 9.3 | I44: Series B | J44: IIFL Fintech Fund; Claypond Capital | K44: https://economictimes.indiatimes.com/tech/funding/fintech-startup-grayquest-raises-rs-80-crore-from-iifl-fintech-fund-ranjan-pais-claypond-capital/articleshow/117088951.cms
A45: INC-20250111-04 | B45: R250109-grayquest | C45: Inc42 | D45: 45666 | E45: GrayQuest | F45: $9.3 Mn | H45: 9.3 | I45: Series B | K45: https://inc42.com/buzz/from-innovaccer-to-beyond-snack-indian-startups-raised-432-mn-this-week/
A46: VCC-121e17de38 | B46: R250109-grayquest | C46: VCCircle | D46: 45666 | E46: howfamilyoffice backers of grayquest are sitting on an upside as it | I46: Series B | K46: https://www.vccircle.com/howfamilyoffice-backers-of-grayquest-are-sitting-on-an-upside-as-it-closes-its-series-b-round
A47: ENT-8603735 | B47: R250109-infinityfincor | C47: Entrackr | D47: 45666 | E47: Infinity Fincorp Solutions | F47: $35 million | H47: 35 | I47: Undisclosed | K47: https://entrackr.com/snippets/infinity-fincorp-solutions-closes-35-mn-round-8603735
A48: ET-117063789 | B48: R250109-infinityfincor | C48: The Economic Times | D48: 45666 | E48: Infinity Fincorp | F48: $15 million | G48: 130 | H48: 15 | I48: Undisclosed | K48: https://economictimes.indiatimes.com/tech/funding/infinity-fincorp-closes-35-million-round-with-15-million-from-jungle-archerman/articleshow/117063789.cms
A49: INC-20250111-03 | B49: R250109-infinityfincor | C49: Inc42 | D49: 45666 | E49: Infinity Fincorp | F49: $35 Mn | H49: 35 | I49: Undisclosed | J49: Jungle Ventures | K49: https://inc42.com/buzz/from-innovaccer-to-beyond-snack-indian-startups-raised-432-mn-this-week/
A50: ET-117092526 | B50: R250109-innovaccer | C50: The Economic Times | D50: 45666 | E50: Innovaccer | F50: $275 million | H50: 275 | I50: Undisclosed | K50: https://economictimes.indiatimes.com/tech/funding/saas-firm-innovaccer-closes-275-million-funding-to-build-more-on-ai-cloud/articleshow/117092526.cms
A51: INC-20250111-01 | B51: R250109-innovaccer | C51: Inc42 | D51: 45666 | E51: Innovaccer | F51: $275 Mn | H51: 275 | I51: Series F | K51: https://inc42.com/buzz/from-innovaccer-to-beyond-snack-indian-startups-raised-432-mn-this-week/
A52: ENT-8606711 | B52: R250109-innovaccer | C52: Entrackr | D52: 45667 | E52: Innovaccer | F52: $275 million | H52: 275 | I52: Series F | K52: https://entrackr.com/news/saas-unicorn-innovaccer-raises-275-mn-in-series-f-round-8606711
A53: VCC-540eb98a2d | B53: R250109-innovaccer | C53: VCCircle | D53: 45667 | E53: innovacer | F53: $ 275 million | H53: 275 | I53: Series F | K53: https://www.vccircle.com/healthcarefocused-saas-unicorn-innovacer-raises-275-mn-in-series-f
A54: ENT-8604374 | B54: R250109-integrishealth | C54: Entrackr | D54: 45666 | E54: Integris Health | I54: Undisclosed | K54: https://entrackr.com/snippets/integris-health-raises-primary-capital-ahead-of-planned-ipo-8604374
A55: INC-20250111-20 | B55: R250109-revivo | C55: Inc42 | D55: 45666 | E55: Revivo | I55: Pre-Series A | J55: Inflection Point Ventures | K55: https://inc42.com/buzz/from-innovaccer-to-beyond-snack-indian-startups-raised-432-mn-this-week/
A56: INC-20250111-11 | B56: R250109-waycool | C56: Inc42 | D56: 45666 | E56: WayCool | F56: $4.4 Mn | H56: 4.4 | I56: Undisclosed | J56: Trifecta Capital | K56: https://inc42.com/buzz/from-innovaccer-to-beyond-snack-indian-startups-raised-432-mn-this-week/
A57: ENT-8608038 | B57: R250110-quash | C57: Entrackr | D57: 45667 | E57: Quash | F57: $635,000 | H57: 0.635 | I57: Pre-Seed | J57: Arali Ventures | K57: https://entrackr.com/snippets/agentic-ai-startup-quash-raises-pre-seed-round-led-by-arali-ventures-8608038
A58: INC-20250111-16 | B58: R250110-quash | C58: Inc42 | D58: 45667 | E58: Quash | F58: $635K | H58: 0.635 | I58: Pre-Seed | J58: Arali Ventures | K58: https://inc42.com/buzz/from-innovaccer-to-beyond-snack-indian-startups-raised-432-mn-this-week/
A59: INC-20250111-15 | B59: R250110-reputai | C59: Inc42 | D59: 45667 | E59: RePut.ai | F59: $1 Mn | H59: 1 | I59: Pre-Seed | J59: GrowthCap Venture | K59: https://inc42.com/buzz/from-innovaccer-to-beyond-snack-indian-startups-raised-432-mn-this-week/
A60: ENT-8619352 | B60: R250110-reputai | C60: Entrackr | D60: 45670 | E60: RePut.ai | F60: $1 million | H60: 1 | I60: Pre-Seed | J60: GrowthCap Ventures | K60: https://entrackr.com/snippets/reputai-closes-1-mn-in-pre-seed-round-led-by-growthcap-ventures-8619352
A61: ENT-8614194 | B61: R250113-bobabhai | C61: Entrackr | D61: 45670 | E61: Boba Bhai | F61: Rs 30 crore | G61: 30 | H61: 3.4 | I61: Series A | J61: 8i Ventures | K61: https://entrackr.com/snippets/bubble-tea-brand-boba-bhai-raises-rs-30-cr-in-series-a-round-8614194
A62: ET-117178912 | B62: R250113-bobabhai | C62: The Economic Times | D62: 45670 | E62: Boba Bhai | F62: Rs 30 crore | G62: 30 | I62: Undisclosed | J62: 8i Ventures | K62: https://economictimes.indiatimes.com/tech/funding/quick-service-restaurant-boba-bhai-raises-rs-30-crore-in-round-led-by-8i-ventures/articleshow/117178912.cms
A63: INC-20250118-13 | B63: R250113-bobabhai | C63: Inc42 | D63: 45670 | E63: Boba Bhai | F63: $3.4 Mn | H63: 3.4 | I63: Series A | J63: 8i Ventures | K63: https://inc42.com/buzz/from-netradyne-to-foxtale-indian-startups-raised-308-mn-this-week/
A64: INC-20250118-02 | B64: R250113-weworkindia | C64: Inc42 | D64: 45670 | E64: WeWork India | F64: $57.7 Mn | H64: 57.7 | I64: Undisclosed | K64: https://inc42.com/buzz/from-netradyne-to-foxtale-indian-startups-raised-308-mn-this-week/
A65: ENT-8620040 | B65: R250114-bgauss | C65: Entrackr | D65: 45671 | E65: BGauss | F65: Rs 161 crore | G65: 161 | H65: 18.6 | I65: Undisclosed | K65: https://entrackr.com/news/ev-two-wheeler-manufacturer-bgauss-raises-rs-161-cr-8620040
A66: ET-117211441 | B66: R250114-bgauss | C66: The Economic Times | D66: 45671 | E66: BGauss | F66: Rs 161 crore | G66: 161 | I66: Undisclosed | K66: https://economictimes.indiatimes.com/tech/funding/electric-two-wheeler-startup-bgauss-raises-rs-161-crore-from-bharat-value-fund/articleshow/117211441.cms
A67: INC-20250118-06 | B67: R250114-bgauss | C67: Inc42 | D67: 45671 | E67: BGauss | F67: $18.6 Mn | H67: 18.6 | I67: Undisclosed | J67: Bharat Value Fund | K67: https://inc42.com/buzz/from-netradyne-to-foxtale-indian-startups-raised-308-mn-this-week/
A68: INC-20250118-07 | B68: R250114-bharatpe | C68: Inc42 | D68: 45671 | E68: BharatPe | F68: $17.3 Mn | H68: 17.3 | I68: Debt | K68: https://inc42.com/buzz/from-netradyne-to-foxtale-indian-startups-raised-308-mn-this-week/
A69: ET-117237257 | B69: R250114-greenstitch | C69: The Economic Times | D69: 45671 | E69: GreenStitch | F69: $1.2 million | H69: 1.2 | I69: Seed | J69: Equirus InnovateX Fund | K69: https://economictimes.indiatimes.com/tech/funding/climate-tech-startup-greenstitch-raises-1-2-million-from-equirus-innovatex-fund-others/articleshow/117237257.cms
A70: ENT-8623238 | B70: R250114-greenstitch | C70: Entrackr | D70: 45672 | E70: GreenStitch | F70: $1.2 million | H70: 1.2 | I70: Seed | J70: Equirus InnovateX Fund | K70: https://entrackr.com/snippets/greenstitch-bags-12-mn-in-seed-round-8623238
A71: ENT-8619966 | B71: R250114-tractorfactory | C71: Entrackr | D71: 45671 | E71: Tractor Factory | F71: Rs 4 crore | G71: 4 | H71: 0.5 | I71: Pre-Seed | J71: All In Capital | K71: https://entrackr.com/snippets/tractor-factory-raises-500k-in-pre-seed-round-led-by-all-in-capital-8619966
A72: INC-20250118-23 | B72: R250114-tractorfactory | C72: Inc42 | D72: 45671 | E72: Tractor Factory | F72: $500K | H72: 0.5 | I72: Pre-Seed | J72: All In Capital | K72: https://inc42.com/buzz/from-netradyne-to-foxtale-indian-startups-raised-308-mn-this-week/
A73: ET-117257400 | B73: R250114-tractorfactory | C73: The Economic Times | D73: 45672 | E73: Tractor Factory | I73: Pre-Seed | J73: All In Capital | K73: https://economictimes.indiatimes.com/tech/funding/pre-owned-tractors-and-farm-equipment-platform-tractor-factory-raises-funding-led-by-all-in-capital/articleshow/117257400.cms
A74: ENT-8622777 | B74: R250115-eccentricengin | C74: Entrackr | D74: 45672 | E74: Eccentric Engine | F74: $5 million | H74: 5 | I74: Pre-Series A | J74: Exfinity Venture Partners; Arkam Ventures | K74: https://entrackr.com/snippets/eccentric-engine-raises-5-mn-in-pre-series-a-round-8622777
A75: ET-117242387 | B75: R250115-eccentricengin | C75: The Economic Times | D75: 45672 | E75: Eccentric | F75: $5 million | H75: 5 | I75: Pre-Series A | J75: Exfinity Venture Partners; Arkam Ventures | K75: https://economictimes.indiatimes.com/tech/funding/automotive-3d-visualisation-startup-eccentric-raises-5-million-in-pre-series-a-funding/articleshow/117242387.cms
A76: INC-20250118-10 | B76: R250115-eccentricengin | C76: Inc42 | D76: 45672 | E76: Eccentric | F76: $5 Mn | H76: 5 | I76: Pre-Series A | J76: Exfinity Venture Partners; Arkam Ventures | K76: https://inc42.com/buzz/from-netradyne-to-foxtale-indian-startups-raised-308-mn-this-week/
A77: ENT-8623678 | B77: R250115-ecozen | C77: Entrackr | D77: 45672 | E77: Ecozen | F77: $23 million | H77: 23 | I77: Debt | K77: https://entrackr.com/news/climate-tech-startup-ecozen-raises-23-mn-in-debt-8623678
A78: INC-20250118-04 | B78: R250115-ecozen | C78: Inc42 | D78: 45672 | E78: Ecozen | F78: $23 Mn | H78: 23 | I78: Debt | K78: https://inc42.com/buzz/from-netradyne-to-foxtale-indian-startups-raised-308-mn-this-week/
A79: INC-20250118-19 | B79: R250115-erlysign | C79: Inc42 | D79: 45672 | E79: ErlySign | F79: $1.8 Mn | H79: 1.8 | I79: Pre-Series A | J79: Ashish Kacholia | K79: https://inc42.com/buzz/from-netradyne-to-foxtale-indian-startups-raised-308-mn-this-week/
A80: ENT-8625920 | B80: R250115-erlysign | C80: Entrackr | D80: 45673 | E80: ErlySign | F80: Rs 16 crore | G80: 16 | H80: 1.8 | I80: Pre-Series A | K80: https://entrackr.com/snippets/erlysign-raises-18-mn-in-pre-series-a-round-from-ashish-kacholia-8625920
A81: INC-20250118-05 | B81: R250115-eulermotors | C81: Inc42 | D81: 45672 | E81: Euler Motors | F81: $20 Mn | H81: 20 | I81: Debt | K81: https://inc42.com/buzz/from-netradyne-to-foxtale-indian-startups-raised-308-mn-this-week/
A82: ENT-8623443 | B82: R250115-foxtale | C82: Entrackr | D82: 45672 | E82: Foxtale | F82: $30 million | G82: 250 | H82: 30 | I82: Undisclosed | J82: Kose Corporation | K82: https://entrackr.com/news/d2c-skincare-brand-foxtale-raises-30-mn-8623443
A83: ET-117259339 | B83: R250115-foxtale | C83: The Economic Times | D83: 45672 | E83: Foxtale | F83: $30 million | G83: 250 | H83: 30 | I83: Undisclosed | J83: Kose Corporation | K83: https://economictimes.indiatimes.com/tech/funding/skincare-brand-foxtale-raises-30-million-led-by-japanese-beauty-firm-kose-corporation/articleshow/117259339.cms
A84: INC-20250118-03 | B84: R250115-foxtale | C84: Inc42 | D84: 45672 | E84: Foxtale | F84: $30 Mn | H84: 30 | I84: Series C | J84: KOSÉ Corporation | K84: https://inc42.com/buzz/from-netradyne-to-foxtale-indian-startups-raised-308-mn-this-week/
A85: ENT-8622828 | B85: R250115-orbitaid | C85: Entrackr | D85: 45672 | E85: OrbitAID | F85: $1.5 million | H85: 1.5 | I85: Pre-Seed | J85: Unicorn India Ventures | K85: https://entrackr.com/snippets/spacetech-startup-orbitaid-raises-15-mn-led-by-unicorn-india-ventures-8622828
A86: ET-117264412 | B86: R250115-orbitaid | C86: The Economic Times | D86: 45672 | E86: OrbitAID | F86: $1.5 million | H86: 1.5 | I86: Pre-Seed | J86: Unicorn India Ventures | K86: https://economictimes.indiatimes.com/tech/funding/spacetech-startup-orbitaid-raises-1-5-million-led-by-unicorn-india-ventures/articleshow/117264412.cms
A87: INC-20250118-21 | B87: R250115-orbitaid | C87: Inc42 | D87: 45672 | E87: OrbitAID | F87: $1.5 Mn | H87: 1.5 | I87: Pre-Seed | J87: Unicorn India Ventures | K87: https://inc42.com/buzz/from-netradyne-to-foxtale-indian-startups-raised-308-mn-this-week/
A88: ENT-8623699 | B88: R250115-parkmate | C88: Entrackr | D88: 45672 | E88: ParkMate | F88: $1.2 million | H88: 1.2 | I88: Undisclosed | J88: Cactus Partners; Marwah Group Family Office | K88: https://entrackr.com/snippets/cactus-partners-leads-12-mn-round-in-parkmate-8623699
A89: INC-20250118-22 | B89: R250115-parkmate | C89: Inc42 | D89: 45673 | E89: ParkMate | F89: $1.2 Mn | H89: 1.2 | I89: Undisclosed | J89: Cactus Partners | K89: https://inc42.com/buzz/from-netradyne-to-foxtale-indian-startups-raised-308-mn-this-week/
A90: ENT-8622762 | B90: R250115-sarlaaviation | C90: Entrackr | D90: 45672 | E90: Sarla Aviation | F90: $10 million | H90: 10 | I90: Undisclosed | J90: Accel | K90: https://entrackr.com/snippets/aerospace-startup-sarla-aviation-raises-10-mn-led-by-accel-8622762
A91: ET-117244903 | B91: R250115-sarlaaviation | C91: The Economic Times | D91: 45672 | E91: Sarla Aviation | F91: $10 million | H91: 10 | I91: Undisclosed | J91: Accel | K91: https://economictimes.indiatimes.com/tech/funding/aerospace-startup-sarla-aviation-raises-10-million-to-build-electric-flying-taxis/articleshow/117244903.cms
A92: INC-20250118-08 | B92: R250115-sarlaaviation | C92: Inc42 | D92: 45672 | E92: Sarla Aviation | F92: $10 Mn | H92: 10 | I92: Series A | J92: Accel | K92: https://inc42.com/buzz/from-netradyne-to-foxtale-indian-startups-raised-308-mn-this-week/
A93: ENT-8622991 | B93: R250115-sukoonunlimite | C93: Entrackr | D93: 45672 | E93: Sukoon Unlimited | F93: $430K | H93: 0.43 | I93: Pre-Seed | K93: https://entrackr.com/snippets/agetech-startup-sukoon-unlimited-raises-pre-seed-round-8622991
A94: INC-20250118-24 | B94: R250115-sukoonunlimite | C94: Inc42 | D94: 45672 | E94: Sukoon Unlimited | F94: $430K | H94: 0.43 | I94: Pre-Seed | K94: https://inc42.com/buzz/from-netradyne-to-foxtale-indian-startups-raised-308-mn-this-week/
A95: ENT-8623233 | B95: R250115-tyreplex | C95: Entrackr | D95: 45672 | E95: TyrePlex | F95: Rs 20 crore | G95: 20 | H95: 2.4 | I95: Undisclosed | J95: PeerCapital | K95: https://entrackr.com/snippets/tyreplex-raises-rs-20-cr-from-peercapital-titan-capital-winners-fund-others-8623233
A96: INC-20250118-15 | B96: R250115-tyreplex | C96: Inc42 | D96: 45672 | E96: TyrePlex | F96: $2.4 Mn | H96: 2.4 | I96: Undisclosed | J96: PeerCapital | K96: https://inc42.com/buzz/from-netradyne-to-foxtale-indian-startups-raised-308-mn-this-week/
A97: ENT-8626771 | B97: R250116-astrosureai | C97: Entrackr | D97: 45673 | E97: AstroSure.ai | F97: $6 million | H97: 6 | I97: Seed | J97: Pradeep Dadha | K97: https://entrackr.com/snippets/astrosureai-raises-6-mn-in-seed-round-8626771
A98: INC-20250118-09 | B98: R250116-astrosureai | C98: Inc42 | D98: 45673 | E98: AstroSure | F98: $6 Mn | H98: 6 | I98: Seed | J98: Pradeep Dadha | K98: https://inc42.com/buzz/from-netradyne-to-foxtale-indian-startups-raised-308-mn-this-week/
A99: ET-117304142 | B99: R250116-constelli | C99: The Economic Times | D99: 45673 | E99: Constelli | F99: $3 million | H99: 3 | I99: Pre-Series A | J99: Pravega Ventures | K99: https://economictimes.indiatimes.com/tech/funding/defence-tech-startup-constelli-raises-3-million-in-pre-series-a-round-led-by-pravega-ventures/articleshow/117304142.cms
A100: INC-20250118-14 | B100: R250116-constelli | C100: Inc42 | D100: 45673 | E100: Constelli | F100: $3 Mn | H100: 3 | I100: Pre-Series A | J100: Pravega Ventures | K100: https://inc42.com/buzz/from-netradyne-to-foxtale-indian-startups-raised-308-mn-this-week/
A101: ENT-8629310 | B101: R250116-constelli | C101: Entrackr | D101: 45674 | E101: Constelli | F101: $3 million | H101: 3 | I101: Pre-Series A | J101: Pravega Ventures | K101: https://entrackr.com/snippets/pravega-ventures-leads-3-mn-pre-series-a-round-in-constelli-8629310
...

Sheet Coverage
A1: Coverage check against Entrackr's weekly report
A2: A control total: the number of funded startups Entrackr counted each week, beside the rounds tracked here.
A4: Week start | B4: Week end | C4: Entrackr: funded startups | D4: Tracker: rounds | E4: Difference | F4: Entrackr: USD mn | G4: Tracker: USD mn
A5: 45656 | B5: 45661 | C5: 8 | D5: 4 | E5: -4 | F5: 33.44 | G5: 77.71
A6: 45663 | B6: 45668 | C6: 27 | D6: 23 | E6: -4 | F6: 466.45 | G6: 377.24
A7: 45670 | B7: 45675 | C7: 37 | D7: 32 | E7: -5 | F7: 780 | G7: 359.65
A8: 45677 | B8: 45682 | C8: 30 | D8: 29 | E8: -1 | F8: 248.87 | G8: 296.95
A9: 45684 | B9: 45689 | C9: 30 | D9: 28 | E9: -2 | F9: 240.85 | G9: 788.11
A10: 45712 | B10: 45717 | C10: 21 | D10: 21 | E10: 0 | F10: 105.87 | G10: 106.65
A11: 45719 | B11: 45724 | C11: 30 | D11: 33 | E11: 3 | F11: 355.02 | G11: 387.66
A12: 45726 | B12: 45731 | C12: 19 | D12: 16 | E12: -3 | F12: 462.27 | G12: 463.11
A13: 45733 | B13: 45738 | C13: 25 | D13: 27 | E13: 2 | F13: 176.44 | G13: 197.5
A14: 45740 | B14: 45745 | C14: 23 | D14: 27 | E14: 4 | F14: 152.49 | G14: 218.21
A15: 45747 | B15: 45752 | C15: 30 | D15: 30 | E15: 0 | F15: 357.29 | G15: 382.86
A16: 45754 | B16: 45759 | C16: 24 | D16: 23 | E16: -1 | F16: 181.21 | G16: 490.81
... A91: 46300 | B91: 46305 | C91: 28 | D91: 29 | E91: 1 | F91: 113.35 | G91: 154.89

Sheet Chart data
A1: Month | B1: Month start | C1: Rounds | D1: Funding USD mn | F1: Stage | G1: Rounds | I1: Sector | J1: Rounds | L1: City | M1: Rounds | O1: These tables feed the Dashboard charts. They are formulas on the Rounds sheet, so they follow any edit.
A2: Jan 25 | B2: 45658 | C2: =COUNTIF(Rounds!$D$2:$D$2179,B2) -> 116 | D2: =SUMIF(Rounds!$D$2:$D$2179,B2,Rounds!$E$2:$E$2179) -> 1899.66 | F2: Pre-Seed | G2: =COUNTIF(Rounds!$H$2:$H$2179,F2) -> 242 | I2: Ecommerce | J2: =COUNTIF(Rounds!$J$2:$J$2179,I2) -> 478 | L2: Bengaluru | M2: =COUNTIF(Rounds!$K$2:$K$2179,L2) -> 461
A3: Feb 25 | B3: 45689 | C3: =COUNTIF(Rounds!$D$2:$D$2179,B3) -> 93 | D3: =SUMIF(Rounds!$D$2:$D$2179,B3,Rounds!$E$2:$E$2179) -> 762.251 | F3: Seed | G3: =COUNTIF(Rounds!$H$2:$H$2179,F3) -> 467 | I3: Fintech | J3: =COUNTIF(Rounds!$J$2:$J$2179,I3) -> 238 | L3: Delhi NCR | M3: =COUNTIF(Rounds!$K$2:$K$2179,L3) -> 283
A4: Mar 25 | B4: 45717 | C4: =COUNTIF(Rounds!$D$2:$D$2179,B4) -> 105 | D4: =SUMIF(Rounds!$D$2:$D$2179,B4,Rounds!$E$2:$E$2179) -> 1451.488 | F4: Angel | G4: =COUNTIF(Rounds!$H$2:$H$2179,F4) -> 9 | I4: Artificial Intelligence | J4: =COUNTIF(Rounds!$J$2:$J$2179,I4) -> 216 | L4: Mumbai | M4: =COUNTIF(Rounds!$K$2:$K$2179,L4) -> 191
A5: Apr 25 | B5: 45748 | C5: =COUNTIF(Rounds!$D$2:$D$2179,B5) -> 120 | D5: =SUMIF(Rounds!$D$2:$D$2179,B5,Rounds!$E$2:$E$2179) -> 1037.828 | F5: Pre-Series A | G5: =COUNTIF(Rounds!$H$2:$H$2179,F5) -> 231 | I5: Enterprise Tech | J5: =COUNTIF(Rounds!$J$2:$J$2179,I5) -> 177 | L5: Pune | M5: =COUNTIF(Rounds!$K$2:$K$2179,L5) -> 52
A6: May 25 | B6: 45778 | C6: =COUNTIF(Rounds!$D$2:$D$2179,B6) -> 103 | D6: =SUMIF(Rounds!$D$2:$D$2179,B6,Rounds!$E$2:$E$2179) -> 1407.817 | F6: Series A | G6: =COUNTIF(Rounds!$H$2:$H$2179,F6) -> 311 | I6: Advanced Hardware & Technology | J6: =COUNTIF(Rounds!$J$2:$J$2179,I6) -> 167 | L6: Chennai | M6: =COUNTIF(Rounds!$K$2:$K$2179,L6) -> 52
A7: Jun 25 | B7: 45809 | C7: =COUNTIF(Rounds!$D$2:$D$2179,B7) -> 95 | D7: =SUMIF(Rounds!$D$2:$D$2179,B7,Rounds!$E$2:$E$2179) -> 1781.969 | F7: Pre-Series B | G7: =COUNTIF(Rounds!$H$2:$H$2179,F7) -> 25 | I7: Cleantech | J7: =COUNTIF(Rounds!$J$2:$J$2179,I7) -> 151 | L7: Hyderabad | M7: =COUNTIF(Rounds!$K$2:$K$2179,L7) -> 51
A8: Jul 25 | B8: 45839 | C8: =COUNTIF(Rounds!$D$2:$D$2179,B8) -> 108 | D8: =SUMIF(Rounds!$D$2:$D$2179,B8,Rounds!$E$2:$E$2179) -> 853.865 | F8: Series B | G8: =COUNTIF(Rounds!$H$2:$H$2179,F8) -> 150 | I8: Healthtech | J8: =COUNTIF(Rounds!$J$2:$J$2179,I8) -> 137 | L8: Ahmedabad | M8: =COUNTIF(Rounds!$K$2:$K$2179,L8) -> 18
A9: Aug 25 | B9: 45870 | C9: =COUNTIF(Rounds!$D$2:$D$2179,B9) -> 90 | D9: =SUMIF(Rounds!$D$2:$D$2179,B9,Rounds!$E$2:$E$2179) -> 890.882 | F9: Pre-Series C | G9: =COUNTIF(Rounds!$H$2:$H$2179,F9) -> 7 | I9: Consumer Services | J9: =COUNTIF(Rounds!$J$2:$J$2179,I9) -> 125 | L9: Jaipur | M9: =COUNTIF(Rounds!$K$2:$K$2179,L9) -> 15
A10: Sep 25 | B10: 45901 | C10: =COUNTIF(Rounds!$D$2:$D$2179,B10) -> 122 | D10: =SUMIF(Rounds!$D$2:$D$2179,B10,Rounds!$E$2:$E$2179) -> 1748.519 | F10: Series C | G10: =COUNTIF(Rounds!$H$2:$H$2179,F10) -> 51 | I10: Media & Entertainment | J10: =COUNTIF(Rounds!$J$2:$J$2179,I10) -> 64 | L10: Kolkata | M10: =COUNTIF(Rounds!$K$2:$K$2179,L10) -> 8
A11: Oct 25 | B11: 45931 | C11: =COUNTIF(Rounds!$D$2:$D$2179,B11) -> 105 | D11: =SUMIF(Rounds!$D$2:$D$2179,B11,Rounds!$E$2:$E$2179) -> 1972.44 | F11: Series D | G11: =COUNTIF(Rounds!$H$2:$H$2179,F11) -> 22 | I11: Deeptech | J11: =COUNTIF(Rounds!$J$2:$J$2179,I11) -> 49 | L11: Chandigarh | M11: =COUNTIF(Rounds!$K$2:$K$2179,L11) -> 7
A12: Nov 25 | B12: 45962 | C12: =COUNTIF(Rounds!$D$2:$D$2179,B12) -> 108 | D12: =SUMIF(Rounds!$D$2:$D$2179,B12,Rounds!$E$2:$E$2179) -> 1167.408 | F12: Series E | G12: =COUNTIF(Rounds!$H$2:$H$2179,F12) -> 11 | I12: Travel Tech | J12: =COUNTIF(Rounds!$J$2:$J$2179,I12) -> 45 | L12: Surat | M12: =COUNTIF(Rounds!$K$2:$K$2179,L12) -> 6
A13: Dec 25 | B13: 45992 | C13: =COUNTIF(Rounds!$D$2:$D$2179,B13) -> 86 | D13: =SUMIF(Rounds!$D$2:$D$2179,B13,Rounds!$E$2:$E$2179) -> 1199.164 | F13: Series F | G13: =COUNTIF(Rounds!$H$2:$H$2179,F13) -> 12 | I13: Agritech | J13: =COUNTIF(Rounds!$J$2:$J$2179,I13) -> 45 | L13: Bhubaneswar | M13: =COUNTIF(Rounds!$K$2:$K$2179,L13) -> 5
A14: Jan 26 | B14: 46023 | C14: =COUNTIF(Rounds!$D$2:$D$2179,B14) -> 115 | D14: =SUMIF(Rounds!$D$2:$D$2179,B14,Rounds!$E$2:$E$2179) -> 951.949 | F14: Series G | G14: =COUNTIF(Rounds!$H$2:$H$2179,F14) -> 6 | I14: Real Estate Tech | J14: =COUNTIF(Rounds!$J$2:$J$2179,I14) -> 45
A15: Feb 26 | B15: 46054 | C15: =COUNTIF(Rounds!$D$2:$D$2179,B15) -> 113 | D15: =SUMIF(Rounds!$D$2:$D$2179,B15,Rounds!$E$2:$E$2179) -> 2194.385 | F15: Series H+ | G15: =COUNTIF(Rounds!$H$2:$H$2179,F15) -> 1 | I15: Edtech | J15: =COUNTIF(Rounds!$J$2:$J$2179,I15) -> 39
A16: Mar 26 | B16: 46082 | C16: =COUNTIF(Rounds!$D$2:$D$2179,B16) -> 103 | D16: =SUMIF(Rounds!$D$2:$D$2179,B16,Rounds!$E$2:$E$2179) -> 1196.683 | F16: Bridge | G16: =COUNTIF(Rounds!$H$2:$H$2179,F16) -> 18
A17: Apr 26 | B17: 46113 | C17: =COUNTIF(Rounds!$D$2:$D$2179,B17) -> 97 | D17: =SUMIF(Rounds!$D$2:$D$2179,B17,Rounds!$E$2:$E$2179) -> 1066.09 | F17: Pre-IPO | G17: =COUNTIF(Rounds!$H$2:$H$2179,F17) -> 9
A18: May 26 | B18: 46143 | C18: =COUNTIF(Rounds!$D$2:$D$2179,B18) -> 73 | D18: =SUMIF(Rounds!$D$2:$D$2179,B18,Rounds!$E$2:$E$2179) -> 707.049 | F18: Debt | G18: =COUNTIF(Rounds!$H$2:$H$2179,F18) -> 79
A19: Jun 26 | B19: 46174 | C19: =COUNTIF(Rounds!$D$2:$D$2179,B19) -> 100 | D19: =SUMIF(Rounds!$D$2:$D$2179,B19,Rounds!$E$2:$E$2179) -> 2153.971 | F19: Undisclosed | G19: =COUNTIF(Rounds!$H$2:$H$2179,F19) -> 527
A20: Jul 26 | B20: 46204 | C20: =COUNTIF(Rounds!$D$2:$D$2179,B20) -> 95 | D20: =SUMIF(Rounds!$D$2:$D$2179,B20,Rounds!$E$2:$E$2179) -> 1043.929
A21: Aug 26 | B21: 46235 | C21: =COUNTIF(Rounds!$D$2:$D$2179,B21) -> 92 | D21: =SUMIF(Rounds!$D$2:$D$2179,B21,Rounds!$E$2:$E$2179) -> 1360.241
A22: Sep 26 | B22: 46266 | C22: =COUNTIF(Rounds!$D$2:$D$2179,B22) -> 105 | D22: =SUMIF(Rounds!$D$2:$D$2179,B22,Rounds!$E$2:$E$2179) -> 1453.458
A23: Oct 26 | B23: 46296 | C23: =COUNTIF(Rounds!$D$2:$D$2179,B23) -> 34 | D23: =SUMIF(Rounds!$D$2:$D$2179,B23,Rounds!$E$2:$E$2179) -> 167.813

Sheet About
A1: About this workbook
A3: What it is | B3: Every Indian startup funding round the tracker found since 01 January 2025, one row per round, with the reports that support it.
A4: Sources | B4: Entrackr and The Economic Times (articles), Inc42 (weekly deal tables), VCCircle (headlines). Only facts and links are stored, never article text.
A5: Reports read | B5: Entrackr 1,752; Inc42 1,771; The Economic Times 761; VCCircle 175 matched to a round.
A6: Exchange rate | B6: Rupee amounts are converted at the ECB reference rate for the announcement date (latest: 96.73 INR per USD on 11 Oct 2026).
A7: PivotTables | B7: By Sector, By Stage and By City are PivotTables on the Rounds table. They refresh when the file opens. After editing data: PivotTable Analyze > Refresh.
A8: Checks | B8: 18 automated checks run on every build. Results are on the Checks and Exceptions sheets.
A9: Rules | B9: The Source rules sheet says which source wins for each field, and why.
A10: Rebuild | B10: python -m funding_tracker update (see README.md in the repository)
A11: Repository | B11: https://github.com/pkjx29/funding-tracker
